{
  "Ввод прав сертификатов подформа 2" : {
    "Properties" : {
      "RecordSource" : "Ввод групп 4",
      "Caption" : "",
      "PopUp" : "false",
      "Modal" : "false",
      "DisplayOnSharePointSite" : 0,
      "DefaultView" : 1,
      "ViewsAllowed" : 1,
      "AllowFormView" : "true",
      "AllowDatasheetView" : "true",
      "AllowPivotTableView" : "true",
      "AllowPivotChartView" : "true",
      "AllowLayoutView" : "false",
      "Picture" : "(отсутствует)",
      "PictureTiling" : "false",
      "PictureAlignment" : 0,
      "PictureType" : 0,
      "PictureSizeMode" : 0,
      "Width" : 10471,
      "AutoCenter" : "true",
      "AutoResize" : "true",
      "FitToScreen" : "false",
      "BorderStyle" : 0,
      "RecordSelectors" : "false",
      "NavigationButtons" : "false",
      "NavigationCaption" : "",
      "DividingLines" : "true",
      "ScrollBars" : 2,
      "ControlBox" : "false",
      "CloseButton" : "true",
      "MinButton" : "false",
      "MaxButton" : "false",
      "MinMaxButtons" : 0,
      "Moveable" : "true",
      "SplitFormSize" : 0,
      "SplitFormOrientation" : 0,
      "SplitFormSplitterBar" : "true",
      "SplitFormDatasheet" : 0,
      "SplitFormPrinting" : 0,
      "SaveSplitterBarPosition" : "true",
      "SubdatasheetExpanded" : "false",
      "SubdatasheetHeight" : 0,
      "GridX" : 6,
      "GridY" : 6,
      "LayoutForPrint" : "false",
      "Orientation" : 0,
      "RecordsetType" : 0,
      "FetchDefaults" : "true",
      "Filter" : "[Флаги]=0",
      "FilterOn" : "true",
      "FilterOnLoad" : "true",
      "OrderBy" : "",
      "OrderByOn" : "false",
      "OrderByOnLoad" : "true",
      "DataEntry" : "false",
      "AllowAdditions" : "false",
      "AllowDeletions" : "false",
      "AllowEdits" : "true",
      "AllowFilters" : "true",
      "OnCurrent" : "",
      "OnCurrentEmMacro" : "",
      "OnLoad" : "",
      "OnLoadEmMacro" : "",
      "OnClick" : "",
      "OnClickEmMacro" : "",
      "AfterUpdate" : "=Inputs_OnSubFormAfterUpdate([Form])",
      "AfterUpdateEmMacro" : "",
      "BeforeUpdate" : "",
      "BeforeUpdateEmMacro" : "",
      "BeforeInsert" : "",
      "BeforeInsertEmMacro" : "",
      "AfterInsert" : "=Inputs_OnSubFormAfterInsert([Form])",
      "AfterInsertEmMacro" : "",
      "BeforeDelConfirm" : "[Event Procedure]",
      "BeforeDelConfirmEmMacro" : "",
      "OnDelete" : "",
      "OnDeleteEmMacro" : "",
      "AfterDelConfirm" : "=Inputs_OnSubFormAfterDelConfirm([Form])",
      "AfterDelConfirmEmMacro" : "",
      "OnDirty" : "",
      "OnDirtyEmMacro" : "",
      "OnGotFocus" : "",
      "OnGotFocusEmMacro" : "",
      "OnLostFocus" : "",
      "OnLostFocusEmMacro" : "",
      "OnDblClick" : "",
      "OnDblClickEmMacro" : "",
      "OnMouseDown" : "",
      "OnMouseDownEmMacro" : "",
      "OnMouseUp" : "",
      "OnMouseUpEmMacro" : "",
      "OnMouseMove" : "",
      "OnMouseMoveEmMacro" : "",
      "OnKeyUp" : "",
      "OnKeyUpEmMacro" : "",
      "OnKeyDown" : "",
      "OnKeyDownEmMacro" : "",
      "OnKeyPress" : "",
      "OnKeyPressEmMacro" : "",
      "OnUndo" : "",
      "OnUndoEmMacro" : "",
      "OnOpen" : "=Inputs_OnSubFormOpen([Form])",
      "OnOpenEmMacro" : "",
      "OnClose" : "=Inputs_OnSubFormClose([Form])",
      "OnCloseEmMacro" : "",
      "OnResize" : "",
      "OnResizeEmMacro" : "",
      "OnActivate" : "",
      "OnActivateEmMacro" : "",
      "OnDeactivate" : "",
      "OnDeactivateEmMacro" : "",
      "OnUnload" : "",
      "OnUnloadEmMacro" : "",
      "OnError" : "[Event Procedure]",
      "OnErrorEmMacro" : "",
      "OnMouseWheel" : "",
      "MouseWheelEmMacro" : "",
      "OnFilter" : "",
      "OnFilterEmMacro" : "",
      "OnApplyFilter" : "",
      "OnApplyFilterEmMacro" : "",
      "OnTimer" : "",
      "OnTimerEmMacro" : "",
      "TimerInterval" : 0,
      "OnSelectionChange" : "",
      "SelectionChangeEmMacro" : "",
      "BeforeRender" : "",
      "BeforeRenderEmMacro" : "",
      "AfterFinalRender" : "",
      "AfterFinalRenderEmMacro" : "",
      "AfterRender" : "",
      "AfterRenderEmMacro" : "",
      "AfterLayout" : "",
      "AfterLayoutEmMacro" : "",
      "OnConnect" : "",
      "OnConnectEmMacro" : "",
      "OnDisconnect" : "",
      "OnDisconnectEmMacro" : "",
      "BeforeQuery" : "",
      "BeforeQueryEmMacro" : "",
      "OnQuery" : "",
      "QueryEmMacro" : "",
      "OnDataChange" : "",
      "DataChangeEmMacro" : "",
      "OnDataSetChange" : "",
      "DataSetChangeEmMacro" : "",
      "OnCmdExecute" : "",
      "CommandExecuteEmMacro" : "",
      "OnCmdBeforeExecute" : "",
      "CommandBeforeExecuteEmMacro" : "",
      "OnCmdEnabled" : "",
      "CommandEnabledEmMacro" : "",
      "OnCmdChecked" : "",
      "CommandCheckedEmMacro" : "",
      "OnViewChange" : "",
      "ViewChangeEmMacro" : "",
      "OnPivotTableChange" : "",
      "PivotTableChangeEmMacro" : "",
      "BeforeScreenTip" : "",
      "BeforeScreenTipEmMacro" : "",
      "Cycle" : 0,
      "RecordLocks" : 2,
      "RibbonName" : "FormButtons",
      "Toolbar" : "",
      "ShortcutMenu" : "true",
      "MenuBar" : "",
      "ShortcutMenuBar" : "Правка",
      "HelpFile" : "Budget15.chm",
      "HelpContextId" : 8001,
      "HasModule" : "true",
      "UseDefaultPaperSize" : "false",
      "FastLaserPrinting" : "true",
      "Tag" : "",
      "PaletteSource" : "(Стандартный)",
      "KeyPreview" : "false",
      "AllowEditing" : "true",
      "DefaultEditing" : 4,
      "AllowUpdating" : 0,
      "RowHeight" : -1,
      "DatasheetFontName" : "Arial Cyr",
      "DatasheetFontHeight" : 10,
      "DatasheetFontWeight" : 400,
      "DatasheetFontItalic" : "false",
      "DatasheetFontUnderline" : "false",
      "DatasheetGridlinesBehavior" : 255,
      "DatasheetGridlinesColor" : 8421504,
      "DatasheetCellsEffect" : 0,
      "DatasheetForeColor" : 0,
      "ShowGrid" : "true",
      "DatasheetBackColor" : 16777215,
      "DatasheetAlternateBackColor" : -2,
      "DatasheetBorderLineStyle" : 1,
      "HorizontalDatasheetGridlineStyle" : 1,
      "VerticalDatasheetGridlineStyle" : 1,
      "DatasheetColumnHeaderUnderlineStyle" : 1,
      "Count" : 33,
      "Visible" : "false",
      "Painting" : "true",
      "FrozenColumns" : 1,
      "Name" : "Ввод прав сертификатов подформа 2",
      "PaintPalette" : "Null",
      "OpenArgs" : "Null",
      "CurrentView" : 0,
      "CurrentSectionTop" : "Null",
      "CurrentSectionLeft" : "Null",
      "SelLeft" : "Null",
      "SelTop" : "Null",
      "SelWidth" : "Null",
      "SelHeight" : "Null",
      "PictureData" : "Null",
      "InsideHeight" : 4590,
      "InsideWidth" : 15720,
      "PicturePalette" : "Null",
      "AllowDesignChanges" : "false"
    },
    "Controls" : {
      "Кнопка Документ" : {
        "Properties" : {
          "EventProcPrefix" : "Кнопка_Документ",
          "Name" : "Кнопка Документ",
          "ControlType" : 100,
          "Caption" : "Наименование типа документа",
          "Visible" : "true",
          "Width" : 3842,
          "Height" : 300,
          "Top" : 15,
          "Left" : 15,
          "BackStyle" : 0,
          "BackColor" : 16777215,
          "BorderStyle" : 0,
          "OldBorderStyle" : 0,
          "BorderLineStyle" : 0,
          "BorderWidth" : 0,
          "BorderColor" : -2147483609,
          "SpecialEffect" : 3,
          "TextFontCharSet" : 204,
          "FontName" : "MS Sans Serif",
          "FontSize" : 8,
          "TextAlign" : 2,
          "FontWeight" : 400,
          "FontUnderline" : "false",
          "FontItalic" : "false",
          "FontBold" : 0,
          "ForeColor" : 0,
          "LineSpacing" : 0,
          "HyperlinkAddress" : "",
          "HyperlinkSubAddress" : "",
          "GridlineStyleTop" : 0,
          "GridlineStyleBottom" : 0,
          "GridlineStyleLeft" : 0,
          "GridlineStyleRight" : 0,
          "GridlineColor" : 0,
          "GridlineWidthTop" : 1,
          "GridlineWidthBottom" : 1,
          "GridlineWidthLeft" : 1,
          "GridlineWidthRight" : 1,
          "TopMargin" : 30,
          "BottomMargin" : 0,
          "LeftMargin" : 30,
          "RightMargin" : 30,
          "TopPadding" : 30,
          "BottomPadding" : 30,
          "LeftPadding" : 30,
          "RightPadding" : 30,
          "HorizontalAnchor" : 2,
          "VerticalAnchor" : 0,
          "DisplayWhen" : 0,
          "ReadingOrder" : 0,
          "NumeralShapes" : 0,
          "OnClick" : "=Inputs_FormSorting([Form],2)",
          "OnClickEmMacro" : "",
          "OnDblClick" : "",
          "OnDblClickEmMacro" : "",
          "OnMouseDown" : "=Inputs_OnControlMouseDown([Form]![Кнопка Документ])",
          "OnMouseDownEmMacro" : "",
          "OnMouseUp" : "=Inputs_OnControlMouseUp([Form]![Кнопка Документ])",
          "OnMouseUpEmMacro" : "",
          "OnMouseMove" : "",
          "OnMouseMoveEmMacro" : "",
          "ControlTipText" : "",
          "ShortcutMenuBar" : "",
          "HelpContextId" : 0,
          "Vertical" : "false",
          "SmartTags" : "",
          "Tag" : "",
          "Section" : 1,
          "InSelection" : "false",
          "Layout" : 0,
          "LayoutID" : 0
        }
      },
      "Кнопка Описание поля" : {
        "Properties" : {
          "EventProcPrefix" : "Кнопка_Описание_поля",
          "Name" : "Кнопка Описание поля",
          "ControlType" : 100,
          "Caption" : "Название состояния",
          "Visible" : "true",
          "Width" : 2010,
          "Height" : 300,
          "Top" : 15,
          "Left" : 3857,
          "BackStyle" : 0,
          "BackColor" : 16777215,
          "BorderStyle" : 0,
          "OldBorderStyle" : 0,
          "BorderLineStyle" : 0,
          "BorderWidth" : 0,
          "BorderColor" : -2147483609,
          "SpecialEffect" : 3,
          "TextFontCharSet" : 204,
          "FontName" : "MS Sans Serif",
          "FontSize" : 8,
          "TextAlign" : 2,
          "FontWeight" : 400,
          "FontUnderline" : "false",
          "FontItalic" : "false",
          "FontBold" : 0,
          "ForeColor" : 0,
          "LineSpacing" : 0,
          "HyperlinkAddress" : "",
          "HyperlinkSubAddress" : "",
          "GridlineStyleTop" : 0,
          "GridlineStyleBottom" : 0,
          "GridlineStyleLeft" : 0,
          "GridlineStyleRight" : 0,
          "GridlineColor" : 0,
          "GridlineWidthTop" : 1,
          "GridlineWidthBottom" : 1,
          "GridlineWidthLeft" : 1,
          "GridlineWidthRight" : 1,
          "TopMargin" : 30,
          "BottomMargin" : 0,
          "LeftMargin" : 30,
          "RightMargin" : 30,
          "TopPadding" : 30,
          "BottomPadding" : 30,
          "LeftPadding" : 30,
          "RightPadding" : 30,
          "HorizontalAnchor" : 1,
          "VerticalAnchor" : 0,
          "DisplayWhen" : 0,
          "ReadingOrder" : 0,
          "NumeralShapes" : 0,
          "OnClick" : "=Inputs_FormSorting([Form],3)",
          "OnClickEmMacro" : "",
          "OnDblClick" : "",
          "OnDblClickEmMacro" : "",
          "OnMouseDown" : "=Inputs_OnControlMouseDown([Form]![Кнопка Описание поля])",
          "OnMouseDownEmMacro" : "",
          "OnMouseUp" : "=Inputs_OnControlMouseUp([Form]![Кнопка Описание поля])",
          "OnMouseUpEmMacro" : "",
          "OnMouseMove" : "",
          "OnMouseMoveEmMacro" : "",
          "ControlTipText" : "",
          "ShortcutMenuBar" : "",
          "HelpContextId" : 0,
          "Vertical" : "false",
          "SmartTags" : "",
          "Tag" : "",
          "Section" : 1,
          "InSelection" : "false",
          "Layout" : 0,
          "LayoutID" : 0
        }
      },
      "Кнопка Признак обязательности ЭЦП" : {
        "Properties" : {
          "EventProcPrefix" : "Кнопка_Признак_обязательности_ЭЦП",
          "Name" : "Кнопка Признак обязательности ЭЦП",
          "ControlType" : 100,
          "Caption" : "ЭП",
          "Visible" : "true",
          "Width" : 512,
          "Height" : 300,
          "Top" : 15,
          "Left" : 6375,
          "BackStyle" : 0,
          "BackColor" : 16777215,
          "BorderStyle" : 0,
          "OldBorderStyle" : 0,
          "BorderLineStyle" : 0,
          "BorderWidth" : 0,
          "BorderColor" : -2147483609,
          "SpecialEffect" : 3,
          "TextFontCharSet" : 204,
          "FontName" : "MS Sans Serif",
          "FontSize" : 8,
          "TextAlign" : 2,
          "FontWeight" : 400,
          "FontUnderline" : "false",
          "FontItalic" : "false",
          "FontBold" : 0,
          "ForeColor" : 0,
          "LineSpacing" : 0,
          "HyperlinkAddress" : "",
          "HyperlinkSubAddress" : "",
          "GridlineStyleTop" : 0,
          "GridlineStyleBottom" : 0,
          "GridlineStyleLeft" : 0,
          "GridlineStyleRight" : 0,
          "GridlineColor" : 0,
          "GridlineWidthTop" : 1,
          "GridlineWidthBottom" : 1,
          "GridlineWidthLeft" : 1,
          "GridlineWidthRight" : 1,
          "TopMargin" : 30,
          "BottomMargin" : 0,
          "LeftMargin" : 30,
          "RightMargin" : 30,
          "TopPadding" : 30,
          "BottomPadding" : 30,
          "LeftPadding" : 30,
          "RightPadding" : 30,
          "HorizontalAnchor" : 1,
          "VerticalAnchor" : 0,
          "DisplayWhen" : 0,
          "ReadingOrder" : 0,
          "NumeralShapes" : 0,
          "OnClick" : "=Inputs_FormSorting([Form],5)",
          "OnClickEmMacro" : "",
          "OnDblClick" : "",
          "OnDblClickEmMacro" : "",
          "OnMouseDown" : "=Inputs_OnControlMouseDown([Form]![Кнопка Признак обязательности ЭЦП])",
          "OnMouseDownEmMacro" : "",
          "OnMouseUp" : "=Inputs_OnControlMouseUp([Form]![Кнопка Признак обязательности ЭЦП])",
          "OnMouseUpEmMacro" : "",
          "OnMouseMove" : "",
          "OnMouseMoveEmMacro" : "",
          "ControlTipText" : "",
          "ShortcutMenuBar" : "",
          "HelpContextId" : 0,
          "Vertical" : "false",
          "SmartTags" : "",
          "Tag" : "",
          "Section" : 1,
          "InSelection" : "false",
          "Layout" : 0,
          "LayoutID" : 0
        }
      },
      "Кнопка Признак вставки своих" : {
        "Properties" : {
          "EventProcPrefix" : "Кнопка_Признак_вставки_своих",
          "Name" : "Кнопка Признак вставки своих",
          "ControlType" : 100,
          "Caption" : "ВС",
          "Visible" : "true",
          "Width" : 512,
          "Height" : 300,
          "Top" : 15,
          "Left" : 6887,
          "BackStyle" : 0,
          "BackColor" : 16777215,
          "BorderStyle" : 0,
          "OldBorderStyle" : 0,
          "BorderLineStyle" : 0,
          "BorderWidth" : 0,
          "BorderColor" : -2147483609,
          "SpecialEffect" : 3,
          "TextFontCharSet" : 204,
          "FontName" : "MS Sans Serif",
          "FontSize" : 8,
          "TextAlign" : 2,
          "FontWeight" : 400,
          "FontUnderline" : "false",
          "FontItalic" : "false",
          "FontBold" : 0,
          "ForeColor" : 0,
          "LineSpacing" : 0,
          "HyperlinkAddress" : "",
          "HyperlinkSubAddress" : "",
          "GridlineStyleTop" : 0,
          "GridlineStyleBottom" : 0,
          "GridlineStyleLeft" : 0,
          "GridlineStyleRight" : 0,
          "GridlineColor" : 0,
          "GridlineWidthTop" : 1,
          "GridlineWidthBottom" : 1,
          "GridlineWidthLeft" : 1,
          "GridlineWidthRight" : 1,
          "TopMargin" : 30,
          "BottomMargin" : 0,
          "LeftMargin" : 30,
          "RightMargin" : 30,
          "TopPadding" : 30,
          "BottomPadding" : 30,
          "LeftPadding" : 30,
          "RightPadding" : 30,
          "HorizontalAnchor" : 1,
          "VerticalAnchor" : 0,
          "DisplayWhen" : 0,
          "ReadingOrder" : 0,
          "NumeralShapes" : 0,
          "OnClick" : "=Inputs_FormSorting([Form],6)",
          "OnClickEmMacro" : "",
          "OnDblClick" : "",
          "OnDblClickEmMacro" : "",
          "OnMouseDown" : "=Inputs_OnControlMouseDown([Form]![Кнопка Признак вставки своих])",
          "OnMouseDownEmMacro" : "",
          "OnMouseUp" : "=Inputs_OnControlMouseUp([Form]![Кнопка Признак вставки своих])",
          "OnMouseUpEmMacro" : "",
          "OnMouseMove" : "",
          "OnMouseMoveEmMacro" : "",
          "ControlTipText" : "",
          "ShortcutMenuBar" : "",
          "HelpContextId" : 0,
          "Vertical" : "false",
          "SmartTags" : "",
          "Tag" : "",
          "Section" : 1,
          "InSelection" : "false",
          "Layout" : 0,
          "LayoutID" : 0
        }
      },
      "Кнопка Признак удаления своих" : {
        "Properties" : {
          "EventProcPrefix" : "Кнопка_Признак_удаления_своих",
          "Name" : "Кнопка Признак удаления своих",
          "ControlType" : 100,
          "Caption" : "УС",
          "Visible" : "true",
          "Width" : 512,
          "Height" : 300,
          "Top" : 15,
          "Left" : 7399,
          "BackStyle" : 0,
          "BackColor" : 16777215,
          "BorderStyle" : 0,
          "OldBorderStyle" : 0,
          "BorderLineStyle" : 0,
          "BorderWidth" : 0,
          "BorderColor" : -2147483609,
          "SpecialEffect" : 3,
          "TextFontCharSet" : 204,
          "FontName" : "MS Sans Serif",
          "FontSize" : 8,
          "TextAlign" : 2,
          "FontWeight" : 400,
          "FontUnderline" : "false",
          "FontItalic" : "false",
          "FontBold" : 0,
          "ForeColor" : 0,
          "LineSpacing" : 0,
          "HyperlinkAddress" : "",
          "HyperlinkSubAddress" : "",
          "GridlineStyleTop" : 0,
          "GridlineStyleBottom" : 0,
          "GridlineStyleLeft" : 0,
          "GridlineStyleRight" : 0,
          "GridlineColor" : 0,
          "GridlineWidthTop" : 1,
          "GridlineWidthBottom" : 1,
          "GridlineWidthLeft" : 1,
          "GridlineWidthRight" : 1,
          "TopMargin" : 30,
          "BottomMargin" : 0,
          "LeftMargin" : 30,
          "RightMargin" : 30,
          "TopPadding" : 30,
          "BottomPadding" : 30,
          "LeftPadding" : 30,
          "RightPadding" : 30,
          "HorizontalAnchor" : 1,
          "VerticalAnchor" : 0,
          "DisplayWhen" : 0,
          "ReadingOrder" : 0,
          "NumeralShapes" : 0,
          "OnClick" : "=Inputs_FormSorting([Form],7)",
          "OnClickEmMacro" : "",
          "OnDblClick" : "",
          "OnDblClickEmMacro" : "",
          "OnMouseDown" : "=Inputs_OnControlMouseDown([Form]![Кнопка Признак удаления своих])",
          "OnMouseDownEmMacro" : "",
          "OnMouseUp" : "=Inputs_OnControlMouseUp([Form]![Кнопка Признак удаления своих])",
          "OnMouseUpEmMacro" : "",
          "OnMouseMove" : "",
          "OnMouseMoveEmMacro" : "",
          "ControlTipText" : "",
          "ShortcutMenuBar" : "",
          "HelpContextId" : 0,
          "Vertical" : "false",
          "SmartTags" : "",
          "Tag" : "",
          "Section" : 1,
          "InSelection" : "false",
          "Layout" : 0,
          "LayoutID" : 0
        }
      },
      "Кнопка Признак вставки чужих" : {
        "Properties" : {
          "EventProcPrefix" : "Кнопка_Признак_вставки_чужих",
          "Name" : "Кнопка Признак вставки чужих",
          "ControlType" : 100,
          "Caption" : "ВЧ",
          "Visible" : "true",
          "Width" : 512,
          "Height" : 300,
          "Top" : 15,
          "Left" : 7911,
          "BackStyle" : 0,
          "BackColor" : 16777215,
          "BorderStyle" : 0,
          "OldBorderStyle" : 0,
          "BorderLineStyle" : 0,
          "BorderWidth" : 0,
          "BorderColor" : -2147483609,
          "SpecialEffect" : 3,
          "TextFontCharSet" : 204,
          "FontName" : "MS Sans Serif",
          "FontSize" : 8,
          "TextAlign" : 2,
          "FontWeight" : 400,
          "FontUnderline" : "false",
          "FontItalic" : "false",
          "FontBold" : 0,
          "ForeColor" : 0,
          "LineSpacing" : 0,
          "HyperlinkAddress" : "",
          "HyperlinkSubAddress" : "",
          "GridlineStyleTop" : 0,
          "GridlineStyleBottom" : 0,
          "GridlineStyleLeft" : 0,
          "GridlineStyleRight" : 0,
          "GridlineColor" : 0,
          "GridlineWidthTop" : 1,
          "GridlineWidthBottom" : 1,
          "GridlineWidthLeft" : 1,
          "GridlineWidthRight" : 1,
          "TopMargin" : 30,
          "BottomMargin" : 0,
          "LeftMargin" : 30,
          "RightMargin" : 30,
          "TopPadding" : 30,
          "BottomPadding" : 30,
          "LeftPadding" : 30,
          "RightPadding" : 30,
          "HorizontalAnchor" : 1,
          "VerticalAnchor" : 0,
          "DisplayWhen" : 0,
          "ReadingOrder" : 0,
          "NumeralShapes" : 0,
          "OnClick" : "=Inputs_FormSorting([Form],8)",
          "OnClickEmMacro" : "",
          "OnDblClick" : "",
          "OnDblClickEmMacro" : "",
          "OnMouseDown" : "=Inputs_OnControlMouseDown([Form]![Кнопка Признак вставки чужих])",
          "OnMouseDownEmMacro" : "",
          "OnMouseUp" : "=Inputs_OnControlMouseUp([Form]![Кнопка Признак вставки чужих])",
          "OnMouseUpEmMacro" : "",
          "OnMouseMove" : "",
          "OnMouseMoveEmMacro" : "",
          "ControlTipText" : "",
          "ShortcutMenuBar" : "",
          "HelpContextId" : 0,
          "Vertical" : "false",
          "SmartTags" : "",
          "Tag" : "",
          "Section" : 1,
          "InSelection" : "false",
          "Layout" : 0,
          "LayoutID" : 0
        }
      },
      "Кнопка Признак удаления чужих" : {
        "Properties" : {
          "EventProcPrefix" : "Кнопка_Признак_удаления_чужих",
          "Name" : "Кнопка Признак удаления чужих",
          "ControlType" : 100,
          "Caption" : "УЧ",
          "Visible" : "true",
          "Width" : 512,
          "Height" : 300,
          "Top" : 15,
          "Left" : 8423,
          "BackStyle" : 0,
          "BackColor" : 16777215,
          "BorderStyle" : 0,
          "OldBorderStyle" : 0,
          "BorderLineStyle" : 0,
          "BorderWidth" : 0,
          "BorderColor" : -2147483609,
          "SpecialEffect" : 3,
          "TextFontCharSet" : 204,
          "FontName" : "MS Sans Serif",
          "FontSize" : 8,
          "TextAlign" : 2,
          "FontWeight" : 400,
          "FontUnderline" : "false",
          "FontItalic" : "false",
          "FontBold" : 0,
          "ForeColor" : 0,
          "LineSpacing" : 0,
          "HyperlinkAddress" : "",
          "HyperlinkSubAddress" : "",
          "GridlineStyleTop" : 0,
          "GridlineStyleBottom" : 0,
          "GridlineStyleLeft" : 0,
          "GridlineStyleRight" : 0,
          "GridlineColor" : 0,
          "GridlineWidthTop" : 1,
          "GridlineWidthBottom" : 1,
          "GridlineWidthLeft" : 1,
          "GridlineWidthRight" : 1,
          "TopMargin" : 30,
          "BottomMargin" : 0,
          "LeftMargin" : 30,
          "RightMargin" : 30,
          "TopPadding" : 30,
          "BottomPadding" : 30,
          "LeftPadding" : 30,
          "RightPadding" : 30,
          "HorizontalAnchor" : 1,
          "VerticalAnchor" : 0,
          "DisplayWhen" : 0,
          "ReadingOrder" : 0,
          "NumeralShapes" : 0,
          "OnClick" : "=Inputs_FormSorting([Form],9)",
          "OnClickEmMacro" : "",
          "OnDblClick" : "",
          "OnDblClickEmMacro" : "",
          "OnMouseDown" : "=Inputs_OnControlMouseDown([Form]![Кнопка Признак удаления чужих])",
          "OnMouseDownEmMacro" : "",
          "OnMouseUp" : "=Inputs_OnControlMouseUp([Form]![Кнопка Признак удаления чужих])",
          "OnMouseUpEmMacro" : "",
          "OnMouseMove" : "",
          "OnMouseMoveEmMacro" : "",
          "ControlTipText" : "",
          "ShortcutMenuBar" : "",
          "HelpContextId" : 0,
          "Vertical" : "false",
          "SmartTags" : "",
          "Tag" : "",
          "Section" : 1,
          "InSelection" : "false",
          "Layout" : 0,
          "LayoutID" : 0
        }
      },
      "Кнопка Признак обновления" : {
        "Properties" : {
          "EventProcPrefix" : "Кнопка_Признак_обновления",
          "Name" : "Кнопка Признак обновления",
          "ControlType" : 100,
          "Caption" : "ОП",
          "Visible" : "true",
          "Width" : 512,
          "Height" : 300,
          "Top" : 15,
          "Left" : 8935,
          "BackStyle" : 0,
          "BackColor" : 16777215,
          "BorderStyle" : 0,
          "OldBorderStyle" : 0,
          "BorderLineStyle" : 0,
          "BorderWidth" : 0,
          "BorderColor" : -2147483609,
          "SpecialEffect" : 3,
          "TextFontCharSet" : 204,
          "FontName" : "MS Sans Serif",
          "FontSize" : 8,
          "TextAlign" : 2,
          "FontWeight" : 400,
          "FontUnderline" : "false",
          "FontItalic" : "false",
          "FontBold" : 0,
          "ForeColor" : 0,
          "LineSpacing" : 0,
          "HyperlinkAddress" : "",
          "HyperlinkSubAddress" : "",
          "GridlineStyleTop" : 0,
          "GridlineStyleBottom" : 0,
          "GridlineStyleLeft" : 0,
          "GridlineStyleRight" : 0,
          "GridlineColor" : 0,
          "GridlineWidthTop" : 1,
          "GridlineWidthBottom" : 1,
          "GridlineWidthLeft" : 1,
          "GridlineWidthRight" : 1,
          "TopMargin" : 30,
          "BottomMargin" : 0,
          "LeftMargin" : 30,
          "RightMargin" : 30,
          "TopPadding" : 30,
          "BottomPadding" : 30,
          "LeftPadding" : 30,
          "RightPadding" : 30,
          "HorizontalAnchor" : 1,
          "VerticalAnchor" : 0,
          "DisplayWhen" : 0,
          "ReadingOrder" : 0,
          "NumeralShapes" : 0,
          "OnClick" : "=Inputs_FormSorting([Form],10)",
          "OnClickEmMacro" : "",
          "OnDblClick" : "",
          "OnDblClickEmMacro" : "",
          "OnMouseDown" : "=Inputs_OnControlMouseDown([Form]![Кнопка Признак обновления])",
          "OnMouseDownEmMacro" : "",
          "OnMouseUp" : "=Inputs_OnControlMouseUp([Form]![Кнопка Признак обновления])",
          "OnMouseUpEmMacro" : "",
          "OnMouseMove" : "",
          "OnMouseMoveEmMacro" : "",
          "ControlTipText" : "",
          "ShortcutMenuBar" : "",
          "HelpContextId" : 0,
          "Vertical" : "false",
          "SmartTags" : "",
          "Tag" : "",
          "Section" : 1,
          "InSelection" : "false",
          "Layout" : 0,
          "LayoutID" : 0
        }
      },
      "Кнопка Признак изменения группы" : {
        "Properties" : {
          "EventProcPrefix" : "Кнопка_Признак_изменения_группы",
          "Name" : "Кнопка Признак изменения группы",
          "ControlType" : 100,
          "Caption" : "ИГ",
          "Visible" : "true",
          "Width" : 512,
          "Height" : 300,
          "Top" : 15,
          "Left" : 9447,
          "BackStyle" : 0,
          "BackColor" : 16777215,
          "BorderStyle" : 0,
          "OldBorderStyle" : 0,
          "BorderLineStyle" : 0,
          "BorderWidth" : 0,
          "BorderColor" : -2147483609,
          "SpecialEffect" : 3,
          "TextFontCharSet" : 204,
          "FontName" : "MS Sans Serif",
          "FontSize" : 8,
          "TextAlign" : 2,
          "FontWeight" : 400,
          "FontUnderline" : "false",
          "FontItalic" : "false",
          "FontBold" : 0,
          "ForeColor" : 0,
          "LineSpacing" : 0,
          "HyperlinkAddress" : "",
          "HyperlinkSubAddress" : "",
          "GridlineStyleTop" : 0,
          "GridlineStyleBottom" : 0,
          "GridlineStyleLeft" : 0,
          "GridlineStyleRight" : 0,
          "GridlineColor" : 0,
          "GridlineWidthTop" : 1,
          "GridlineWidthBottom" : 1,
          "GridlineWidthLeft" : 1,
          "GridlineWidthRight" : 1,
          "TopMargin" : 30,
          "BottomMargin" : 0,
          "LeftMargin" : 30,
          "RightMargin" : 30,
          "TopPadding" : 30,
          "BottomPadding" : 30,
          "LeftPadding" : 30,
          "RightPadding" : 30,
          "HorizontalAnchor" : 1,
          "VerticalAnchor" : 0,
          "DisplayWhen" : 0,
          "ReadingOrder" : 0,
          "NumeralShapes" : 0,
          "OnClick" : "=Inputs_FormSorting([Form],11)",
          "OnClickEmMacro" : "",
          "OnDblClick" : "",
          "OnDblClickEmMacro" : "",
          "OnMouseDown" : "=Inputs_OnControlMouseDown([Form]![Кнопка Признак изменения группы])",
          "OnMouseDownEmMacro" : "",
          "OnMouseUp" : "=Inputs_OnControlMouseUp([Form]![Кнопка Признак изменения группы])",
          "OnMouseUpEmMacro" : "",
          "OnMouseMove" : "",
          "OnMouseMoveEmMacro" : "",
          "ControlTipText" : "",
          "ShortcutMenuBar" : "",
          "HelpContextId" : 0,
          "Vertical" : "false",
          "SmartTags" : "",
          "Tag" : "",
          "Section" : 1,
          "InSelection" : "false",
          "Layout" : 0,
          "LayoutID" : 0
        }
      },
      "Кнопка Признак изменения комментария" : {
        "Properties" : {
          "EventProcPrefix" : "Кнопка_Признак_изменения_комментария",
          "Name" : "Кнопка Признак изменения комментария",
          "ControlType" : 100,
          "Caption" : "ИК",
          "Visible" : "true",
          "Width" : 512,
          "Height" : 300,
          "Top" : 15,
          "Left" : 9959,
          "BackStyle" : 0,
          "BackColor" : 16777215,
          "BorderStyle" : 0,
          "OldBorderStyle" : 0,
          "BorderLineStyle" : 0,
          "BorderWidth" : 0,
          "BorderColor" : -2147483609,
          "SpecialEffect" : 3,
          "TextFontCharSet" : 204,
          "FontName" : "MS Sans Serif",
          "FontSize" : 8,
          "TextAlign" : 2,
          "FontWeight" : 400,
          "FontUnderline" : "false",
          "FontItalic" : "false",
          "FontBold" : 0,
          "ForeColor" : 0,
          "LineSpacing" : 0,
          "HyperlinkAddress" : "",
          "HyperlinkSubAddress" : "",
          "GridlineStyleTop" : 0,
          "GridlineStyleBottom" : 0,
          "GridlineStyleLeft" : 0,
          "GridlineStyleRight" : 0,
          "GridlineColor" : 0,
          "GridlineWidthTop" : 1,
          "GridlineWidthBottom" : 1,
          "GridlineWidthLeft" : 1,
          "GridlineWidthRight" : 1,
          "TopMargin" : 30,
          "BottomMargin" : 0,
          "LeftMargin" : 30,
          "RightMargin" : 30,
          "TopPadding" : 30,
          "BottomPadding" : 30,
          "LeftPadding" : 30,
          "RightPadding" : 30,
          "HorizontalAnchor" : 1,
          "VerticalAnchor" : 0,
          "DisplayWhen" : 0,
          "ReadingOrder" : 0,
          "NumeralShapes" : 0,
          "OnClick" : "=Inputs_FormSorting([Form],12)",
          "OnClickEmMacro" : "",
          "OnDblClick" : "",
          "OnDblClickEmMacro" : "",
          "OnMouseDown" : "=Inputs_OnControlMouseDown([Form]![Кнопка Признак изменения комментария])",
          "OnMouseDownEmMacro" : "",
          "OnMouseUp" : "=Inputs_OnControlMouseUp([Form]![Кнопка Признак изменения комментария])",
          "OnMouseUpEmMacro" : "",
          "OnMouseMove" : "",
          "OnMouseMoveEmMacro" : "",
          "ControlTipText" : "",
          "ShortcutMenuBar" : "",
          "HelpContextId" : 0,
          "Vertical" : "false",
          "SmartTags" : "",
          "Tag" : "",
          "Section" : 1,
          "InSelection" : "false",
          "Layout" : 0,
          "LayoutID" : 0
        }
      },
      "Кнопка Признак проверки ЭЦП" : {
        "Properties" : {
          "EventProcPrefix" : "Кнопка_Признак_проверки_ЭЦП",
          "Name" : "Кнопка Признак проверки ЭЦП",
          "ControlType" : 100,
          "Caption" : "ПЭ",
          "Visible" : "true",
          "Width" : 512,
          "Height" : 300,
          "Top" : 15,
          "Left" : 5865,
          "BackStyle" : 0,
          "BackColor" : 16777215,
          "BorderStyle" : 0,
          "OldBorderStyle" : 0,
          "BorderLineStyle" : 0,
          "BorderWidth" : 0,
          "BorderColor" : -2147483609,
          "SpecialEffect" : 3,
          "TextFontCharSet" : 204,
          "FontName" : "MS Sans Serif",
          "FontSize" : 8,
          "TextAlign" : 2,
          "FontWeight" : 400,
          "FontUnderline" : "false",
          "FontItalic" : "false",
          "FontBold" : 0,
          "ForeColor" : 0,
          "LineSpacing" : 0,
          "HyperlinkAddress" : "",
          "HyperlinkSubAddress" : "",
          "GridlineStyleTop" : 0,
          "GridlineStyleBottom" : 0,
          "GridlineStyleLeft" : 0,
          "GridlineStyleRight" : 0,
          "GridlineColor" : 0,
          "GridlineWidthTop" : 1,
          "GridlineWidthBottom" : 1,
          "GridlineWidthLeft" : 1,
          "GridlineWidthRight" : 1,
          "TopMargin" : 30,
          "BottomMargin" : 0,
          "LeftMargin" : 30,
          "RightMargin" : 30,
          "TopPadding" : 30,
          "BottomPadding" : 30,
          "LeftPadding" : 30,
          "RightPadding" : 30,
          "HorizontalAnchor" : 1,
          "VerticalAnchor" : 0,
          "DisplayWhen" : 0,
          "ReadingOrder" : 0,
          "NumeralShapes" : 0,
          "OnClick" : "=Inputs_FormSorting([Form],4)",
          "OnClickEmMacro" : "",
          "OnDblClick" : "",
          "OnDblClickEmMacro" : "",
          "OnMouseDown" : "=Inputs_OnControlMouseDown([Form]![Кнопка Признак проверки ЭЦП])",
          "OnMouseDownEmMacro" : "",
          "OnMouseUp" : "=Inputs_OnControlMouseUp([Form]![Кнопка Признак проверки ЭЦП])",
          "OnMouseUpEmMacro" : "",
          "OnMouseMove" : "",
          "OnMouseMoveEmMacro" : "",
          "ControlTipText" : "",
          "ShortcutMenuBar" : "",
          "HelpContextId" : 0,
          "Vertical" : "false",
          "SmartTags" : "",
          "Tag" : "",
          "Section" : 1,
          "InSelection" : "false",
          "Layout" : 0,
          "LayoutID" : 0
        }
      },
      "Рамка Признак обновления" : {
        "Properties" : {
          "EventProcPrefix" : "Рамка_Признак_обновления",
          "Name" : "Рамка Признак обновления",
          "ControlType" : 101,
          "Visible" : "true",
          "Width" : 512,
          "Height" : 240,
          "Top" : 0,
          "Left" : 8920,
          "BackStyle" : 1,
          "BackColor" : 16777215,
          "BorderStyle" : 1,
          "OldBorderStyle" : 1,
          "BorderLineStyle" : 0,
          "BorderWidth" : 0,
          "BorderColor" : -2147483609,
          "SpecialEffect" : 0,
          "GridlineStyleTop" : 0,
          "GridlineStyleBottom" : 0,
          "GridlineStyleLeft" : 0,
          "GridlineStyleRight" : 0,
          "GridlineColor" : 0,
          "GridlineWidthTop" : 1,
          "GridlineWidthBottom" : 1,
          "GridlineWidthLeft" : 1,
          "GridlineWidthRight" : 1,
          "TopPadding" : 30,
          "BottomPadding" : 30,
          "LeftPadding" : 30,
          "RightPadding" : 30,
          "HorizontalAnchor" : 1,
          "VerticalAnchor" : 0,
          "DisplayWhen" : 0,
          "OnClick" : "",
          "OnClickEmMacro" : "",
          "OnDblClick" : "",
          "OnDblClickEmMacro" : "",
          "OnMouseDown" : "",
          "OnMouseDownEmMacro" : "",
          "OnMouseUp" : "",
          "OnMouseUpEmMacro" : "",
          "OnMouseMove" : "",
          "OnMouseMoveEmMacro" : "",
          "Tag" : "",
          "Section" : 0,
          "InSelection" : "false",
          "Layout" : 0,
          "LayoutID" : 0
        }
      },
      "Документ" : {
        "Properties" : {
          "EventProcPrefix" : "Документ",
          "Name" : "Документ",
          "ControlType" : 109,
          "ControlSource" : "Документ",
          "Format" : "",
          "DecimalPlaces" : 255,
          "Visible" : "true",
          "TextFormat" : 0,
          "DatasheetCaption" : "",
          "ShowDatePicker" : 1,
          "Width" : 3842,
          "Height" : 240,
          "Top" : 0,
          "Left" : 0,
          "BackStyle" : 1,
          "BackColor" : -2147483643,
          "BorderStyle" : 1,
          "OldBorderStyle" : 1,
          "BorderLineStyle" : 0,
          "BorderWidth" : 0,
          "BorderColor" : -2147483609,
          "SpecialEffect" : 0,
          "ScrollBars" : 0,
          "TextFontCharSet" : 204,
          "FontName" : "MS Sans Serif",
          "FontSize" : 8,
          "TextAlign" : 1,
          "FontWeight" : 400,
          "FontUnderline" : "false",
          "FontItalic" : "false",
          "FontBold" : 0,
          "ForeColor" : 0,
          "LineSpacing" : 0,
          "IsHyperlink" : "false",
          "DisplayAsHyperlink" : 0,
          "GridlineStyleTop" : 0,
          "GridlineStyleBottom" : 0,
          "GridlineStyleLeft" : 0,
          "GridlineStyleRight" : 0,
          "GridlineColor" : 0,
          "GridlineWidthTop" : 1,
          "GridlineWidthBottom" : 1,
          "GridlineWidthLeft" : 1,
          "GridlineWidthRight" : 1,
          "TopMargin" : 0,
          "BottomMargin" : 0,
          "LeftMargin" : 0,
          "RightMargin" : 0,
          "TopPadding" : 30,
          "BottomPadding" : 30,
          "LeftPadding" : 30,
          "RightPadding" : 30,
          "HorizontalAnchor" : 2,
          "VerticalAnchor" : 0,
          "CanGrow" : "false",
          "CanShrink" : "false",
          "DisplayWhen" : 0,
          "ReadingOrder" : 0,
          "ScrollBarAlign" : 0,
          "NumeralShapes" : 0,
          "KeyboardLanguage" : 0,
          "InputMask" : "",
          "DefaultValue" : "",
          "ValidationRule" : "",
          "ValidationText" : "",
          "FilterLookup" : 1,
          "Enabled" : "true",
          "Locked" : "true",
          "OnClick" : "",
          "OnClickEmMacro" : "",
          "BeforeUpdate" : "",
          "BeforeUpdateEmMacro" : "",
          "AfterUpdate" : "=Inputs_OnControlAfterUpdate([Form]![Документ])",
          "AfterUpdateEmMacro" : "",
          "OnDirty" : "",
          "OnDirtyEmMacro" : "",
          "OnChange" : "=Inputs_OnControlChange([Form]![Документ])",
          "OnChangeEmMacro" : "",
          "OnGotFocus" : "",
          "OnGotFocusEmMacro" : "",
          "OnLostFocus" : "",
          "OnLostFocusEmMacro" : "",
          "OnDblClick" : "=Inputs_OnControlDblClick([Form]![Документ])",
          "OnDblClickEmMacro" : "",
          "OnMouseDown" : "",
          "OnMouseDownEmMacro" : "",
          "OnMouseUp" : "",
          "OnMouseUpEmMacro" : "",
          "OnMouseMove" : "",
          "OnMouseMoveEmMacro" : "",
          "OnKeyDown" : "",
          "OnKeyDownEmMacro" : "",
          "OnKeyUp" : "",
          "OnKeyUpEmMacro" : "",
          "OnKeyPress" : "",
          "OnKeyPressEmMacro" : "",
          "OnEnter" : "=Inputs_OnControlEnter([Form]![Документ])",
          "OnEnterEmMacro" : "",
          "OnExit" : "=Inputs_OnControlExit([Form]![Документ])",
          "OnExitEmMacro" : "",
          "OnUndo" : "",
          "OnUndoEmMacro" : "",
          "EnterKeyBehavior" : "false",
          "ControlTipText" : "",
          "TabIndex" : 0,
          "TabStop" : "false",
          "StatusBarText" : "Документ",
          "ShortcutMenuBar" : "Правка и сортировка",
          "HelpContextId" : 0,
          "AutoTab" : "false",
          "Vertical" : "false",
          "AllowAutoCorrect" : "true",
          "IMEHold" : "false",
          "IMEMode" : 0,
          "IMESentenceMode" : 0,
          "SmartTags" : "",
          "Tag" : "",
          "ConditionalFormat" : "Null",
          "FuriganaControl" : "",
          "ColumnWidth" : -1,
          "ColumnOrder" : 0,
          "ColumnHidden" : "false",
          "Section" : 0,
          "Text" : "Null",
          "SelText" : "Null",
          "SelStart" : "Null",
          "SelLength" : "Null",
          "InSelection" : "false",
          "AggregateType" : -1,
          "Layout" : 0,
          "LayoutID" : 0
        }
      },
      "Описание поля" : {
        "Properties" : {
          "EventProcPrefix" : "Описание_поля",
          "Name" : "Описание поля",
          "ControlType" : 109,
          "ControlSource" : "Описание поля",
          "Format" : "",
          "DecimalPlaces" : 255,
          "Visible" : "true",
          "TextFormat" : 0,
          "DatasheetCaption" : "",
          "ShowDatePicker" : 1,
          "Width" : 2010,
          "Height" : 240,
          "Top" : 0,
          "Left" : 3842,
          "BackStyle" : 1,
          "BackColor" : -2147483643,
          "BorderStyle" : 1,
          "OldBorderStyle" : 1,
          "BorderLineStyle" : 0,
          "BorderWidth" : 0,
          "BorderColor" : -2147483609,
          "SpecialEffect" : 0,
          "ScrollBars" : 0,
          "TextFontCharSet" : 204,
          "FontName" : "MS Sans Serif",
          "FontSize" : 8,
          "TextAlign" : 1,
          "FontWeight" : 400,
          "FontUnderline" : "false",
          "FontItalic" : "false",
          "FontBold" : 0,
          "ForeColor" : 0,
          "LineSpacing" : 0,
          "IsHyperlink" : "false",
          "DisplayAsHyperlink" : 0,
          "GridlineStyleTop" : 0,
          "GridlineStyleBottom" : 0,
          "GridlineStyleLeft" : 0,
          "GridlineStyleRight" : 0,
          "GridlineColor" : 0,
          "GridlineWidthTop" : 1,
          "GridlineWidthBottom" : 1,
          "GridlineWidthLeft" : 1,
          "GridlineWidthRight" : 1,
          "TopMargin" : 0,
          "BottomMargin" : 0,
          "LeftMargin" : 0,
          "RightMargin" : 0,
          "TopPadding" : 30,
          "BottomPadding" : 30,
          "LeftPadding" : 30,
          "RightPadding" : 30,
          "HorizontalAnchor" : 1,
          "VerticalAnchor" : 0,
          "CanGrow" : "false",
          "CanShrink" : "false",
          "DisplayWhen" : 0,
          "ReadingOrder" : 0,
          "ScrollBarAlign" : 0,
          "NumeralShapes" : 0,
          "KeyboardLanguage" : 0,
          "InputMask" : "",
          "DefaultValue" : "",
          "ValidationRule" : "",
          "ValidationText" : "",
          "FilterLookup" : 1,
          "Enabled" : "true",
          "Locked" : "true",
          "OnClick" : "",
          "OnClickEmMacro" : "",
          "BeforeUpdate" : "",
          "BeforeUpdateEmMacro" : "",
          "AfterUpdate" : "=Inputs_OnControlAfterUpdate([Form]![Описание поля])",
          "AfterUpdateEmMacro" : "",
          "OnDirty" : "",
          "OnDirtyEmMacro" : "",
          "OnChange" : "=Inputs_OnControlChange([Form]![Описание поля])",
          "OnChangeEmMacro" : "",
          "OnGotFocus" : "",
          "OnGotFocusEmMacro" : "",
          "OnLostFocus" : "",
          "OnLostFocusEmMacro" : "",
          "OnDblClick" : "=Inputs_OnControlDblClick([Form]![Описание поля])",
          "OnDblClickEmMacro" : "",
          "OnMouseDown" : "",
          "OnMouseDownEmMacro" : "",
          "OnMouseUp" : "",
          "OnMouseUpEmMacro" : "",
          "OnMouseMove" : "",
          "OnMouseMoveEmMacro" : "",
          "OnKeyDown" : "",
          "OnKeyDownEmMacro" : "",
          "OnKeyUp" : "",
          "OnKeyUpEmMacro" : "",
          "OnKeyPress" : "",
          "OnKeyPressEmMacro" : "",
          "OnEnter" : "=Inputs_OnControlEnter([Form]![Описание поля])",
          "OnEnterEmMacro" : "",
          "OnExit" : "=Inputs_OnControlExit([Form]![Описание поля])",
          "OnExitEmMacro" : "",
          "OnUndo" : "",
          "OnUndoEmMacro" : "",
          "EnterKeyBehavior" : "false",
          "ControlTipText" : "",
          "TabIndex" : 1,
          "TabStop" : "false",
          "StatusBarText" : "Наименование поля",
          "ShortcutMenuBar" : "Правка и сортировка",
          "HelpContextId" : 0,
          "AutoTab" : "false",
          "Vertical" : "false",
          "AllowAutoCorrect" : "true",
          "IMEHold" : "false",
          "IMEMode" : 0,
          "IMESentenceMode" : 0,
          "SmartTags" : "",
          "Tag" : "",
          "ConditionalFormat" : "Null",
          "FuriganaControl" : "",
          "ColumnWidth" : -1,
          "ColumnOrder" : 0,
          "ColumnHidden" : "false",
          "Section" : 0,
          "Text" : "Null",
          "SelText" : "Null",
          "SelStart" : "Null",
          "SelLength" : "Null",
          "InSelection" : "false",
          "AggregateType" : -1,
          "Layout" : 0,
          "LayoutID" : 0
        }
      },
      "Рамка Признак вставки" : {
        "Properties" : {
          "EventProcPrefix" : "Рамка_Признак_вставки",
          "Name" : "Рамка Признак вставки",
          "ControlType" : 101,
          "Visible" : "true",
          "Width" : 512,
          "Height" : 240,
          "Top" : 0,
          "Left" : 6872,
          "BackStyle" : 1,
          "BackColor" : 16777215,
          "BorderStyle" : 1,
          "OldBorderStyle" : 1,
          "BorderLineStyle" : 0,
          "BorderWidth" : 0,
          "BorderColor" : -2147483609,
          "SpecialEffect" : 0,
          "GridlineStyleTop" : 0,
          "GridlineStyleBottom" : 0,
          "GridlineStyleLeft" : 0,
          "GridlineStyleRight" : 0,
          "GridlineColor" : 0,
          "GridlineWidthTop" : 1,
          "GridlineWidthBottom" : 1,
          "GridlineWidthLeft" : 1,
          "GridlineWidthRight" : 1,
          "TopPadding" : 30,
          "BottomPadding" : 30,
          "LeftPadding" : 30,
          "RightPadding" : 30,
          "HorizontalAnchor" : 1,
          "VerticalAnchor" : 0,
          "DisplayWhen" : 0,
          "OnClick" : "",
          "OnClickEmMacro" : "",
          "OnDblClick" : "",
          "OnDblClickEmMacro" : "",
          "OnMouseDown" : "",
          "OnMouseDownEmMacro" : "",
          "OnMouseUp" : "",
          "OnMouseUpEmMacro" : "",
          "OnMouseMove" : "",
          "OnMouseMoveEmMacro" : "",
          "Tag" : "",
          "Section" : 0,
          "InSelection" : "false",
          "Layout" : 0,
          "LayoutID" : 0
        }
      },
      "Признак вставки своих" : {
        "Properties" : {
          "EventProcPrefix" : "Признак_вставки_своих",
          "Name" : "Признак вставки своих",
          "ControlType" : 106,
          "ControlSource" : "Признак вставки своих",
          "Visible" : "true",
          "TripleState" : "false",
          "Width" : 170,
          "Height" : 180,
          "Top" : 45,
          "Left" : 7050,
          "BorderStyle" : 1,
          "OldBorderStyle" : 1,
          "BorderLineStyle" : 0,
          "BorderWidth" : 0,
          "BorderColor" : 0,
          "SpecialEffect" : 5,
          "GridlineStyleTop" : 0,
          "GridlineStyleBottom" : 0,
          "GridlineStyleLeft" : 0,
          "GridlineStyleRight" : 0,
          "GridlineColor" : 0,
          "GridlineWidthTop" : 1,
          "GridlineWidthBottom" : 1,
          "GridlineWidthLeft" : 1,
          "GridlineWidthRight" : 1,
          "TopPadding" : 30,
          "BottomPadding" : 30,
          "LeftPadding" : 30,
          "RightPadding" : 30,
          "HorizontalAnchor" : 1,
          "VerticalAnchor" : 0,
          "DisplayWhen" : 0,
          "ReadingOrder" : 0,
          "DefaultValue" : "",
          "ValidationRule" : "",
          "ValidationText" : "",
          "Enabled" : "true",
          "Locked" : "false",
          "OnClick" : "",
          "OnClickEmMacro" : "",
          "BeforeUpdate" : "",
          "BeforeUpdateEmMacro" : "",
          "AfterUpdate" : "=Inputs_OnControlAfterUpdate([Form]![Признак вставки своих])",
          "AfterUpdateEmMacro" : "",
          "OnGotFocus" : "",
          "OnGotFocusEmMacro" : "",
          "OnLostFocus" : "",
          "OnLostFocusEmMacro" : "",
          "OnDblClick" : "=Inputs_OnControlDblClick([Form]![Признак вставки своих])",
          "OnDblClickEmMacro" : "",
          "OnMouseDown" : "",
          "OnMouseDownEmMacro" : "",
          "OnMouseUp" : "",
          "OnMouseUpEmMacro" : "",
          "OnMouseMove" : "",
          "OnMouseMoveEmMacro" : "",
          "OnKeyDown" : "",
          "OnKeyDownEmMacro" : "",
          "OnKeyUp" : "",
          "OnKeyUpEmMacro" : "",
          "OnKeyPress" : "",
          "OnKeyPressEmMacro" : "",
          "OnEnter" : "=Inputs_OnControlEnter([Form]![Признак вставки своих])",
          "OnEnterEmMacro" : "",
          "OnExit" : "=Inputs_OnControlExit([Form]![Признак вставки своих])",
          "OnExitEmMacro" : "",
          "ControlTipText" : "",
          "TabIndex" : 3,
          "TabStop" : "true",
          "StatusBarText" : "Признак допустимости установки состояния \"своих\" документов",
          "ShortcutMenuBar" : "",
          "HelpContextId" : 0,
          "Tag" : "",
          "ColumnWidth" : -1,
          "ColumnOrder" : 0,
          "ColumnHidden" : "false",
          "Section" : 0,
          "InSelection" : "false",
          "AggregateType" : -1,
          "Layout" : 0,
          "LayoutID" : 0
        }
      },
      "Рамка Признак удаления" : {
        "Properties" : {
          "EventProcPrefix" : "Рамка_Признак_удаления",
          "Name" : "Рамка Признак удаления",
          "ControlType" : 101,
          "Visible" : "true",
          "Width" : 512,
          "Height" : 240,
          "Top" : 0,
          "Left" : 7384,
          "BackStyle" : 1,
          "BackColor" : 16777215,
          "BorderStyle" : 1,
          "OldBorderStyle" : 1,
          "BorderLineStyle" : 0,
          "BorderWidth" : 0,
          "BorderColor" : -2147483609,
          "SpecialEffect" : 0,
          "GridlineStyleTop" : 0,
          "GridlineStyleBottom" : 0,
          "GridlineStyleLeft" : 0,
          "GridlineStyleRight" : 0,
          "GridlineColor" : 0,
          "GridlineWidthTop" : 1,
          "GridlineWidthBottom" : 1,
          "GridlineWidthLeft" : 1,
          "GridlineWidthRight" : 1,
          "TopPadding" : 30,
          "BottomPadding" : 30,
          "LeftPadding" : 30,
          "RightPadding" : 30,
          "HorizontalAnchor" : 1,
          "VerticalAnchor" : 0,
          "DisplayWhen" : 0,
          "OnClick" : "",
          "OnClickEmMacro" : "",
          "OnDblClick" : "",
          "OnDblClickEmMacro" : "",
          "OnMouseDown" : "",
          "OnMouseDownEmMacro" : "",
          "OnMouseUp" : "",
          "OnMouseUpEmMacro" : "",
          "OnMouseMove" : "",
          "OnMouseMoveEmMacro" : "",
          "Tag" : "",
          "Section" : 0,
          "InSelection" : "false",
          "Layout" : 0,
          "LayoutID" : 0
        }
      },
      "Признак удаления своих" : {
        "Properties" : {
          "EventProcPrefix" : "Признак_удаления_своих",
          "Name" : "Признак удаления своих",
          "ControlType" : 106,
          "ControlSource" : "Признак удаления своих",
          "Visible" : "true",
          "TripleState" : "false",
          "Width" : 170,
          "Height" : 180,
          "Top" : 45,
          "Left" : 7565,
          "BorderStyle" : 1,
          "OldBorderStyle" : 1,
          "BorderLineStyle" : 0,
          "BorderWidth" : 0,
          "BorderColor" : 0,
          "SpecialEffect" : 5,
          "GridlineStyleTop" : 0,
          "GridlineStyleBottom" : 0,
          "GridlineStyleLeft" : 0,
          "GridlineStyleRight" : 0,
          "GridlineColor" : 0,
          "GridlineWidthTop" : 1,
          "GridlineWidthBottom" : 1,
          "GridlineWidthLeft" : 1,
          "GridlineWidthRight" : 1,
          "TopPadding" : 30,
          "BottomPadding" : 30,
          "LeftPadding" : 30,
          "RightPadding" : 30,
          "HorizontalAnchor" : 1,
          "VerticalAnchor" : 0,
          "DisplayWhen" : 0,
          "ReadingOrder" : 0,
          "DefaultValue" : "",
          "ValidationRule" : "",
          "ValidationText" : "",
          "Enabled" : "true",
          "Locked" : "false",
          "OnClick" : "",
          "OnClickEmMacro" : "",
          "BeforeUpdate" : "",
          "BeforeUpdateEmMacro" : "",
          "AfterUpdate" : "=Inputs_OnControlAfterUpdate([Form]![Признак удаления своих])",
          "AfterUpdateEmMacro" : "",
          "OnGotFocus" : "",
          "OnGotFocusEmMacro" : "",
          "OnLostFocus" : "",
          "OnLostFocusEmMacro" : "",
          "OnDblClick" : "=Inputs_OnControlDblClick([Form]![Признак удаления своих])",
          "OnDblClickEmMacro" : "",
          "OnMouseDown" : "",
          "OnMouseDownEmMacro" : "",
          "OnMouseUp" : "",
          "OnMouseUpEmMacro" : "",
          "OnMouseMove" : "",
          "OnMouseMoveEmMacro" : "",
          "OnKeyDown" : "",
          "OnKeyDownEmMacro" : "",
          "OnKeyUp" : "",
          "OnKeyUpEmMacro" : "",
          "OnKeyPress" : "",
          "OnKeyPressEmMacro" : "",
          "OnEnter" : "=Inputs_OnControlEnter([Form]![Признак удаления своих])",
          "OnEnterEmMacro" : "",
          "OnExit" : "=Inputs_OnControlExit([Form]![Признак удаления своих])",
          "OnExitEmMacro" : "",
          "ControlTipText" : "",
          "TabIndex" : 4,
          "TabStop" : "true",
          "StatusBarText" : "Признак допустимости отмены состояния \"своих\" документов",
          "ShortcutMenuBar" : "",
          "HelpContextId" : 0,
          "Tag" : "",
          "ColumnWidth" : -1,
          "ColumnOrder" : 0,
          "ColumnHidden" : "false",
          "Section" : 0,
          "InSelection" : "false",
          "AggregateType" : -1,
          "Layout" : 0,
          "LayoutID" : 0
        }
      },
      "Рамка Признак вставки чужих" : {
        "Properties" : {
          "EventProcPrefix" : "Рамка_Признак_вставки_чужих",
          "Name" : "Рамка Признак вставки чужих",
          "ControlType" : 101,
          "Visible" : "true",
          "Width" : 512,
          "Height" : 240,
          "Top" : 0,
          "Left" : 7896,
          "BackStyle" : 1,
          "BackColor" : 16777215,
          "BorderStyle" : 1,
          "OldBorderStyle" : 1,
          "BorderLineStyle" : 0,
          "BorderWidth" : 0,
          "BorderColor" : -2147483609,
          "SpecialEffect" : 0,
          "GridlineStyleTop" : 0,
          "GridlineStyleBottom" : 0,
          "GridlineStyleLeft" : 0,
          "GridlineStyleRight" : 0,
          "GridlineColor" : 0,
          "GridlineWidthTop" : 1,
          "GridlineWidthBottom" : 1,
          "GridlineWidthLeft" : 1,
          "GridlineWidthRight" : 1,
          "TopPadding" : 30,
          "BottomPadding" : 30,
          "LeftPadding" : 30,
          "RightPadding" : 30,
          "HorizontalAnchor" : 1,
          "VerticalAnchor" : 0,
          "DisplayWhen" : 0,
          "OnClick" : "",
          "OnClickEmMacro" : "",
          "OnDblClick" : "",
          "OnDblClickEmMacro" : "",
          "OnMouseDown" : "",
          "OnMouseDownEmMacro" : "",
          "OnMouseUp" : "",
          "OnMouseUpEmMacro" : "",
          "OnMouseMove" : "",
          "OnMouseMoveEmMacro" : "",
          "Tag" : "",
          "Section" : 0,
          "InSelection" : "false",
          "Layout" : 0,
          "LayoutID" : 0
        }
      },
      "Признак вставки чужих" : {
        "Properties" : {
          "EventProcPrefix" : "Признак_вставки_чужих",
          "Name" : "Признак вставки чужих",
          "ControlType" : 106,
          "ControlSource" : "Признак вставки чужих",
          "Visible" : "true",
          "TripleState" : "false",
          "Width" : 170,
          "Height" : 180,
          "Top" : 45,
          "Left" : 8080,
          "BorderStyle" : 1,
          "OldBorderStyle" : 1,
          "BorderLineStyle" : 0,
          "BorderWidth" : 0,
          "BorderColor" : 0,
          "SpecialEffect" : 5,
          "GridlineStyleTop" : 0,
          "GridlineStyleBottom" : 0,
          "GridlineStyleLeft" : 0,
          "GridlineStyleRight" : 0,
          "GridlineColor" : 0,
          "GridlineWidthTop" : 1,
          "GridlineWidthBottom" : 1,
          "GridlineWidthLeft" : 1,
          "GridlineWidthRight" : 1,
          "TopPadding" : 30,
          "BottomPadding" : 30,
          "LeftPadding" : 30,
          "RightPadding" : 30,
          "HorizontalAnchor" : 1,
          "VerticalAnchor" : 0,
          "DisplayWhen" : 0,
          "ReadingOrder" : 0,
          "DefaultValue" : "",
          "ValidationRule" : "",
          "ValidationText" : "",
          "Enabled" : "true",
          "Locked" : "false",
          "OnClick" : "",
          "OnClickEmMacro" : "",
          "BeforeUpdate" : "",
          "BeforeUpdateEmMacro" : "",
          "AfterUpdate" : "=Inputs_OnControlAfterUpdate([Form]![Признак вставки чужих])",
          "AfterUpdateEmMacro" : "",
          "OnGotFocus" : "",
          "OnGotFocusEmMacro" : "",
          "OnLostFocus" : "",
          "OnLostFocusEmMacro" : "",
          "OnDblClick" : "=Inputs_OnControlDblClick([Form]![Признак вставки чужих])",
          "OnDblClickEmMacro" : "",
          "OnMouseDown" : "",
          "OnMouseDownEmMacro" : "",
          "OnMouseUp" : "",
          "OnMouseUpEmMacro" : "",
          "OnMouseMove" : "",
          "OnMouseMoveEmMacro" : "",
          "OnKeyDown" : "",
          "OnKeyDownEmMacro" : "",
          "OnKeyUp" : "",
          "OnKeyUpEmMacro" : "",
          "OnKeyPress" : "",
          "OnKeyPressEmMacro" : "",
          "OnEnter" : "=Inputs_OnControlEnter([Form]![Признак вставки чужих])",
          "OnEnterEmMacro" : "",
          "OnExit" : "=Inputs_OnControlExit([Form]![Признак вставки чужих])",
          "OnExitEmMacro" : "",
          "ControlTipText" : "",
          "TabIndex" : 5,
          "TabStop" : "true",
          "StatusBarText" : "Признак допустимости установки состояния \"чужих\" документов",
          "ShortcutMenuBar" : "",
          "HelpContextId" : 0,
          "Tag" : "",
          "ColumnWidth" : -1,
          "ColumnOrder" : 0,
          "ColumnHidden" : "false",
          "Section" : 0,
          "InSelection" : "false",
          "AggregateType" : -1,
          "Layout" : 0,
          "LayoutID" : 0
        }
      },
      "Рамка Признак удаления чужих" : {
        "Properties" : {
          "EventProcPrefix" : "Рамка_Признак_удаления_чужих",
          "Name" : "Рамка Признак удаления чужих",
          "ControlType" : 101,
          "Visible" : "true",
          "Width" : 512,
          "Height" : 240,
          "Top" : 0,
          "Left" : 8408,
          "BackStyle" : 1,
          "BackColor" : 16777215,
          "BorderStyle" : 1,
          "OldBorderStyle" : 1,
          "BorderLineStyle" : 0,
          "BorderWidth" : 0,
          "BorderColor" : -2147483609,
          "SpecialEffect" : 0,
          "GridlineStyleTop" : 0,
          "GridlineStyleBottom" : 0,
          "GridlineStyleLeft" : 0,
          "GridlineStyleRight" : 0,
          "GridlineColor" : 0,
          "GridlineWidthTop" : 1,
          "GridlineWidthBottom" : 1,
          "GridlineWidthLeft" : 1,
          "GridlineWidthRight" : 1,
          "TopPadding" : 30,
          "BottomPadding" : 30,
          "LeftPadding" : 30,
          "RightPadding" : 30,
          "HorizontalAnchor" : 1,
          "VerticalAnchor" : 0,
          "DisplayWhen" : 0,
          "OnClick" : "",
          "OnClickEmMacro" : "",
          "OnDblClick" : "",
          "OnDblClickEmMacro" : "",
          "OnMouseDown" : "",
          "OnMouseDownEmMacro" : "",
          "OnMouseUp" : "",
          "OnMouseUpEmMacro" : "",
          "OnMouseMove" : "",
          "OnMouseMoveEmMacro" : "",
          "Tag" : "",
          "Section" : 0,
          "InSelection" : "false",
          "Layout" : 0,
          "LayoutID" : 0
        }
      },
      "Признак удаления чужих" : {
        "Properties" : {
          "EventProcPrefix" : "Признак_удаления_чужих",
          "Name" : "Признак удаления чужих",
          "ControlType" : 106,
          "ControlSource" : "Признак удаления чужих",
          "Visible" : "true",
          "TripleState" : "false",
          "Width" : 170,
          "Height" : 180,
          "Top" : 45,
          "Left" : 8595,
          "BorderStyle" : 1,
          "OldBorderStyle" : 1,
          "BorderLineStyle" : 0,
          "BorderWidth" : 0,
          "BorderColor" : 0,
          "SpecialEffect" : 5,
          "GridlineStyleTop" : 0,
          "GridlineStyleBottom" : 0,
          "GridlineStyleLeft" : 0,
          "GridlineStyleRight" : 0,
          "GridlineColor" : 0,
          "GridlineWidthTop" : 1,
          "GridlineWidthBottom" : 1,
          "GridlineWidthLeft" : 1,
          "GridlineWidthRight" : 1,
          "TopPadding" : 30,
          "BottomPadding" : 30,
          "LeftPadding" : 30,
          "RightPadding" : 30,
          "HorizontalAnchor" : 1,
          "VerticalAnchor" : 0,
          "DisplayWhen" : 0,
          "ReadingOrder" : 0,
          "DefaultValue" : "",
          "ValidationRule" : "",
          "ValidationText" : "",
          "Enabled" : "true",
          "Locked" : "false",
          "OnClick" : "",
          "OnClickEmMacro" : "",
          "BeforeUpdate" : "",
          "BeforeUpdateEmMacro" : "",
          "AfterUpdate" : "=Inputs_OnControlAfterUpdate([Form]![Признак удаления чужих])",
          "AfterUpdateEmMacro" : "",
          "OnGotFocus" : "",
          "OnGotFocusEmMacro" : "",
          "OnLostFocus" : "",
          "OnLostFocusEmMacro" : "",
          "OnDblClick" : "=Inputs_OnControlDblClick([Form]![Признак удаления чужих])",
          "OnDblClickEmMacro" : "",
          "OnMouseDown" : "",
          "OnMouseDownEmMacro" : "",
          "OnMouseUp" : "",
          "OnMouseUpEmMacro" : "",
          "OnMouseMove" : "",
          "OnMouseMoveEmMacro" : "",
          "OnKeyDown" : "",
          "OnKeyDownEmMacro" : "",
          "OnKeyUp" : "",
          "OnKeyUpEmMacro" : "",
          "OnKeyPress" : "",
          "OnKeyPressEmMacro" : "",
          "OnEnter" : "=Inputs_OnControlEnter([Form]![Признак удаления чужих])",
          "OnEnterEmMacro" : "",
          "OnExit" : "=Inputs_OnControlExit([Form]![Признак удаления чужих])",
          "OnExitEmMacro" : "",
          "ControlTipText" : "",
          "TabIndex" : 6,
          "TabStop" : "true",
          "StatusBarText" : "Признак допустимости отмены состояния \"чужих\" документов",
          "ShortcutMenuBar" : "",
          "HelpContextId" : 0,
          "Tag" : "",
          "ColumnWidth" : -1,
          "ColumnOrder" : 0,
          "ColumnHidden" : "false",
          "Section" : 0,
          "InSelection" : "false",
          "AggregateType" : -1,
          "Layout" : 0,
          "LayoutID" : 0
        }
      },
      "Признак обновления" : {
        "Properties" : {
          "EventProcPrefix" : "Признак_обновления",
          "Name" : "Признак обновления",
          "ControlType" : 106,
          "ControlSource" : "Признак обновления",
          "Visible" : "true",
          "TripleState" : "false",
          "Width" : 170,
          "Height" : 180,
          "Top" : 45,
          "Left" : 9110,
          "BorderStyle" : 1,
          "OldBorderStyle" : 1,
          "BorderLineStyle" : 0,
          "BorderWidth" : 0,
          "BorderColor" : 0,
          "SpecialEffect" : 5,
          "GridlineStyleTop" : 0,
          "GridlineStyleBottom" : 0,
          "GridlineStyleLeft" : 0,
          "GridlineStyleRight" : 0,
          "GridlineColor" : 0,
          "GridlineWidthTop" : 1,
          "GridlineWidthBottom" : 1,
          "GridlineWidthLeft" : 1,
          "GridlineWidthRight" : 1,
          "TopPadding" : 30,
          "BottomPadding" : 30,
          "LeftPadding" : 30,
          "RightPadding" : 30,
          "HorizontalAnchor" : 1,
          "VerticalAnchor" : 0,
          "DisplayWhen" : 0,
          "ReadingOrder" : 0,
          "DefaultValue" : "",
          "ValidationRule" : "",
          "ValidationText" : "",
          "Enabled" : "true",
          "Locked" : "false",
          "OnClick" : "",
          "OnClickEmMacro" : "",
          "BeforeUpdate" : "",
          "BeforeUpdateEmMacro" : "",
          "AfterUpdate" : "=Inputs_OnControlAfterUpdate([Form]![Признак вставки своих])",
          "AfterUpdateEmMacro" : "",
          "OnGotFocus" : "",
          "OnGotFocusEmMacro" : "",
          "OnLostFocus" : "",
          "OnLostFocusEmMacro" : "",
          "OnDblClick" : "=Inputs_OnControlDblClick([Form]![Признак вставки своих])",
          "OnDblClickEmMacro" : "",
          "OnMouseDown" : "",
          "OnMouseDownEmMacro" : "",
          "OnMouseUp" : "",
          "OnMouseUpEmMacro" : "",
          "OnMouseMove" : "",
          "OnMouseMoveEmMacro" : "",
          "OnKeyDown" : "",
          "OnKeyDownEmMacro" : "",
          "OnKeyUp" : "",
          "OnKeyUpEmMacro" : "",
          "OnKeyPress" : "",
          "OnKeyPressEmMacro" : "",
          "OnEnter" : "=Inputs_OnControlEnter([Form]![Признак вставки своих])",
          "OnEnterEmMacro" : "",
          "OnExit" : "=Inputs_OnControlExit([Form]![Признак вставки своих])",
          "OnExitEmMacro" : "",
          "ControlTipText" : "",
          "TabIndex" : 7,
          "TabStop" : "true",
          "StatusBarText" : "Признак допустимости обновления состояния для переданных документов",
          "ShortcutMenuBar" : "",
          "HelpContextId" : 0,
          "Tag" : "",
          "ColumnWidth" : -1,
          "ColumnOrder" : 0,
          "ColumnHidden" : "false",
          "Section" : 0,
          "InSelection" : "false",
          "AggregateType" : -1,
          "Layout" : 0,
          "LayoutID" : 0
        }
      },
      "Рамка Признак изменения группы" : {
        "Properties" : {
          "EventProcPrefix" : "Рамка_Признак_изменения_группы",
          "Name" : "Рамка Признак изменения группы",
          "ControlType" : 101,
          "Visible" : "true",
          "Width" : 512,
          "Height" : 240,
          "Top" : 0,
          "Left" : 9432,
          "BackStyle" : 1,
          "BackColor" : 16777215,
          "BorderStyle" : 1,
          "OldBorderStyle" : 1,
          "BorderLineStyle" : 0,
          "BorderWidth" : 0,
          "BorderColor" : -2147483609,
          "SpecialEffect" : 0,
          "GridlineStyleTop" : 0,
          "GridlineStyleBottom" : 0,
          "GridlineStyleLeft" : 0,
          "GridlineStyleRight" : 0,
          "GridlineColor" : 0,
          "GridlineWidthTop" : 1,
          "GridlineWidthBottom" : 1,
          "GridlineWidthLeft" : 1,
          "GridlineWidthRight" : 1,
          "TopPadding" : 30,
          "BottomPadding" : 30,
          "LeftPadding" : 30,
          "RightPadding" : 30,
          "HorizontalAnchor" : 1,
          "VerticalAnchor" : 0,
          "DisplayWhen" : 0,
          "OnClick" : "",
          "OnClickEmMacro" : "",
          "OnDblClick" : "",
          "OnDblClickEmMacro" : "",
          "OnMouseDown" : "",
          "OnMouseDownEmMacro" : "",
          "OnMouseUp" : "",
          "OnMouseUpEmMacro" : "",
          "OnMouseMove" : "",
          "OnMouseMoveEmMacro" : "",
          "Tag" : "",
          "Section" : 0,
          "InSelection" : "false",
          "Layout" : 0,
          "LayoutID" : 0
        }
      },
      "Рамка Признак изменения комментария" : {
        "Properties" : {
          "EventProcPrefix" : "Рамка_Признак_изменения_комментария",
          "Name" : "Рамка Признак изменения комментария",
          "ControlType" : 101,
          "Visible" : "true",
          "Width" : 512,
          "Height" : 240,
          "Top" : 0,
          "Left" : 9944,
          "BackStyle" : 1,
          "BackColor" : 16777215,
          "BorderStyle" : 1,
          "OldBorderStyle" : 1,
          "BorderLineStyle" : 0,
          "BorderWidth" : 0,
          "BorderColor" : -2147483609,
          "SpecialEffect" : 0,
          "GridlineStyleTop" : 0,
          "GridlineStyleBottom" : 0,
          "GridlineStyleLeft" : 0,
          "GridlineStyleRight" : 0,
          "GridlineColor" : 0,
          "GridlineWidthTop" : 1,
          "GridlineWidthBottom" : 1,
          "GridlineWidthLeft" : 1,
          "GridlineWidthRight" : 1,
          "TopPadding" : 30,
          "BottomPadding" : 30,
          "LeftPadding" : 30,
          "RightPadding" : 30,
          "HorizontalAnchor" : 1,
          "VerticalAnchor" : 0,
          "DisplayWhen" : 0,
          "OnClick" : "",
          "OnClickEmMacro" : "",
          "OnDblClick" : "",
          "OnDblClickEmMacro" : "",
          "OnMouseDown" : "",
          "OnMouseDownEmMacro" : "",
          "OnMouseUp" : "",
          "OnMouseUpEmMacro" : "",
          "OnMouseMove" : "",
          "OnMouseMoveEmMacro" : "",
          "Tag" : "",
          "Section" : 0,
          "InSelection" : "false",
          "Layout" : 0,
          "LayoutID" : 0
        }
      },
      "Признак изменения группы" : {
        "Properties" : {
          "EventProcPrefix" : "Признак_изменения_группы",
          "Name" : "Признак изменения группы",
          "ControlType" : 106,
          "ControlSource" : "Признак изменения группы",
          "Visible" : "true",
          "TripleState" : "false",
          "Width" : 170,
          "Height" : 180,
          "Top" : 45,
          "Left" : 9625,
          "BorderStyle" : 1,
          "OldBorderStyle" : 1,
          "BorderLineStyle" : 0,
          "BorderWidth" : 0,
          "BorderColor" : 0,
          "SpecialEffect" : 5,
          "GridlineStyleTop" : 0,
          "GridlineStyleBottom" : 0,
          "GridlineStyleLeft" : 0,
          "GridlineStyleRight" : 0,
          "GridlineColor" : 0,
          "GridlineWidthTop" : 1,
          "GridlineWidthBottom" : 1,
          "GridlineWidthLeft" : 1,
          "GridlineWidthRight" : 1,
          "TopPadding" : 30,
          "BottomPadding" : 30,
          "LeftPadding" : 30,
          "RightPadding" : 30,
          "HorizontalAnchor" : 1,
          "VerticalAnchor" : 0,
          "DisplayWhen" : 0,
          "ReadingOrder" : 0,
          "DefaultValue" : "",
          "ValidationRule" : "",
          "ValidationText" : "",
          "Enabled" : "true",
          "Locked" : "false",
          "OnClick" : "",
          "OnClickEmMacro" : "",
          "BeforeUpdate" : "",
          "BeforeUpdateEmMacro" : "",
          "AfterUpdate" : "=Inputs_OnControlAfterUpdate([Form]![Признак изменения группы])",
          "AfterUpdateEmMacro" : "",
          "OnGotFocus" : "",
          "OnGotFocusEmMacro" : "",
          "OnLostFocus" : "",
          "OnLostFocusEmMacro" : "",
          "OnDblClick" : "=Inputs_OnControlDblClick([Form]![Признак изменения группы])",
          "OnDblClickEmMacro" : "",
          "OnMouseDown" : "",
          "OnMouseDownEmMacro" : "",
          "OnMouseUp" : "",
          "OnMouseUpEmMacro" : "",
          "OnMouseMove" : "",
          "OnMouseMoveEmMacro" : "",
          "OnKeyDown" : "",
          "OnKeyDownEmMacro" : "",
          "OnKeyUp" : "",
          "OnKeyUpEmMacro" : "",
          "OnKeyPress" : "",
          "OnKeyPressEmMacro" : "",
          "OnEnter" : "=Inputs_OnControlEnter([Form]![Признак изменения группы])",
          "OnEnterEmMacro" : "",
          "OnExit" : "=Inputs_OnControlExit([Form]![Признак изменения группы])",
          "OnExitEmMacro" : "",
          "ControlTipText" : "",
          "TabIndex" : 8,
          "TabStop" : "true",
          "StatusBarText" : "Признак допустимости изменения группы документа в данном состоянии",
          "ShortcutMenuBar" : "",
          "HelpContextId" : 0,
          "Tag" : "",
          "ColumnWidth" : -1,
          "ColumnOrder" : 0,
          "ColumnHidden" : "false",
          "Section" : 0,
          "InSelection" : "false",
          "AggregateType" : -1,
          "Layout" : 0,
          "LayoutID" : 0
        }
      },
      "Признак изменения комментария" : {
        "Properties" : {
          "EventProcPrefix" : "Признак_изменения_комментария",
          "Name" : "Признак изменения комментария",
          "ControlType" : 106,
          "ControlSource" : "Признак изменения комментария",
          "Visible" : "true",
          "TripleState" : "false",
          "Width" : 170,
          "Height" : 180,
          "Top" : 45,
          "Left" : 10140,
          "BorderStyle" : 1,
          "OldBorderStyle" : 1,
          "BorderLineStyle" : 0,
          "BorderWidth" : 0,
          "BorderColor" : 0,
          "SpecialEffect" : 5,
          "GridlineStyleTop" : 0,
          "GridlineStyleBottom" : 0,
          "GridlineStyleLeft" : 0,
          "GridlineStyleRight" : 0,
          "GridlineColor" : 0,
          "GridlineWidthTop" : 1,
          "GridlineWidthBottom" : 1,
          "GridlineWidthLeft" : 1,
          "GridlineWidthRight" : 1,
          "TopPadding" : 30,
          "BottomPadding" : 30,
          "LeftPadding" : 30,
          "RightPadding" : 30,
          "HorizontalAnchor" : 1,
          "VerticalAnchor" : 0,
          "DisplayWhen" : 0,
          "ReadingOrder" : 0,
          "DefaultValue" : "",
          "ValidationRule" : "",
          "ValidationText" : "",
          "Enabled" : "true",
          "Locked" : "false",
          "OnClick" : "",
          "OnClickEmMacro" : "",
          "BeforeUpdate" : "",
          "BeforeUpdateEmMacro" : "",
          "AfterUpdate" : "=Inputs_OnControlAfterUpdate([Form]![Признак изменения комментария])",
          "AfterUpdateEmMacro" : "",
          "OnGotFocus" : "",
          "OnGotFocusEmMacro" : "",
          "OnLostFocus" : "",
          "OnLostFocusEmMacro" : "",
          "OnDblClick" : "=Inputs_OnControlDblClick([Form]![Признак изменения комментария])",
          "OnDblClickEmMacro" : "",
          "OnMouseDown" : "",
          "OnMouseDownEmMacro" : "",
          "OnMouseUp" : "",
          "OnMouseUpEmMacro" : "",
          "OnMouseMove" : "",
          "OnMouseMoveEmMacro" : "",
          "OnKeyDown" : "",
          "OnKeyDownEmMacro" : "",
          "OnKeyUp" : "",
          "OnKeyUpEmMacro" : "",
          "OnKeyPress" : "",
          "OnKeyPressEmMacro" : "",
          "OnEnter" : "=Inputs_OnControlEnter([Form]![Признак изменения комментария])",
          "OnEnterEmMacro" : "",
          "OnExit" : "=Inputs_OnControlExit([Form]![Признак изменения комментария])",
          "OnExitEmMacro" : "",
          "ControlTipText" : "",
          "TabIndex" : 9,
          "TabStop" : "true",
          "StatusBarText" : "Признак допустимости изменения комментария \"своего\" документа в данном состоянии",
          "ShortcutMenuBar" : "",
          "HelpContextId" : 0,
          "Tag" : "",
          "ColumnWidth" : -1,
          "ColumnOrder" : 0,
          "ColumnHidden" : "false",
          "Section" : 0,
          "InSelection" : "false",
          "AggregateType" : -1,
          "Layout" : 0,
          "LayoutID" : 0
        }
      },
      "Рамка Признак обязательности ЭЦП" : {
        "Properties" : {
          "EventProcPrefix" : "Рамка_Признак_обязательности_ЭЦП",
          "Name" : "Рамка Признак обязательности ЭЦП",
          "ControlType" : 101,
          "Visible" : "true",
          "Width" : 512,
          "Height" : 240,
          "Top" : 0,
          "Left" : 6360,
          "BackStyle" : 1,
          "BackColor" : 16777215,
          "BorderStyle" : 1,
          "OldBorderStyle" : 1,
          "BorderLineStyle" : 0,
          "BorderWidth" : 0,
          "BorderColor" : -2147483609,
          "SpecialEffect" : 0,
          "GridlineStyleTop" : 0,
          "GridlineStyleBottom" : 0,
          "GridlineStyleLeft" : 0,
          "GridlineStyleRight" : 0,
          "GridlineColor" : 0,
          "GridlineWidthTop" : 1,
          "GridlineWidthBottom" : 1,
          "GridlineWidthLeft" : 1,
          "GridlineWidthRight" : 1,
          "TopPadding" : 30,
          "BottomPadding" : 30,
          "LeftPadding" : 30,
          "RightPadding" : 30,
          "HorizontalAnchor" : 1,
          "VerticalAnchor" : 0,
          "DisplayWhen" : 0,
          "OnClick" : "",
          "OnClickEmMacro" : "",
          "OnDblClick" : "",
          "OnDblClickEmMacro" : "",
          "OnMouseDown" : "",
          "OnMouseDownEmMacro" : "",
          "OnMouseUp" : "",
          "OnMouseUpEmMacro" : "",
          "OnMouseMove" : "",
          "OnMouseMoveEmMacro" : "",
          "Tag" : "",
          "Section" : 0,
          "InSelection" : "false",
          "Layout" : 0,
          "LayoutID" : 0
        }
      },
      "Признак обязательности ЭЦП" : {
        "Properties" : {
          "EventProcPrefix" : "Признак_обязательности_ЭЦП",
          "Name" : "Признак обязательности ЭЦП",
          "ControlType" : 106,
          "ControlSource" : "Признак обязательности ЭЦП",
          "Visible" : "true",
          "TripleState" : "false",
          "Width" : 170,
          "Height" : 180,
          "Top" : 45,
          "Left" : 6538,
          "BorderStyle" : 1,
          "OldBorderStyle" : 1,
          "BorderLineStyle" : 0,
          "BorderWidth" : 0,
          "BorderColor" : 0,
          "SpecialEffect" : 5,
          "GridlineStyleTop" : 0,
          "GridlineStyleBottom" : 0,
          "GridlineStyleLeft" : 0,
          "GridlineStyleRight" : 0,
          "GridlineColor" : 0,
          "GridlineWidthTop" : 1,
          "GridlineWidthBottom" : 1,
          "GridlineWidthLeft" : 1,
          "GridlineWidthRight" : 1,
          "TopPadding" : 30,
          "BottomPadding" : 30,
          "LeftPadding" : 30,
          "RightPadding" : 30,
          "HorizontalAnchor" : 1,
          "VerticalAnchor" : 0,
          "DisplayWhen" : 0,
          "ReadingOrder" : 0,
          "DefaultValue" : "",
          "ValidationRule" : "",
          "ValidationText" : "",
          "Enabled" : "true",
          "Locked" : "false",
          "OnClick" : "",
          "OnClickEmMacro" : "",
          "BeforeUpdate" : "",
          "BeforeUpdateEmMacro" : "",
          "AfterUpdate" : "=Inputs_OnControlAfterUpdate([Form]![Признак обязательности ЭЦП])",
          "AfterUpdateEmMacro" : "",
          "OnGotFocus" : "",
          "OnGotFocusEmMacro" : "",
          "OnLostFocus" : "",
          "OnLostFocusEmMacro" : "",
          "OnDblClick" : "=Inputs_OnControlDblClick([Form]![Признак обязательности ЭЦП])",
          "OnDblClickEmMacro" : "",
          "OnMouseDown" : "",
          "OnMouseDownEmMacro" : "",
          "OnMouseUp" : "",
          "OnMouseUpEmMacro" : "",
          "OnMouseMove" : "",
          "OnMouseMoveEmMacro" : "",
          "OnKeyDown" : "",
          "OnKeyDownEmMacro" : "",
          "OnKeyUp" : "",
          "OnKeyUpEmMacro" : "",
          "OnKeyPress" : "",
          "OnKeyPressEmMacro" : "",
          "OnEnter" : "=Inputs_OnControlEnter([Form]![Признак обязательности ЭЦП])",
          "OnEnterEmMacro" : "",
          "OnExit" : "=Inputs_OnControlExit([Form]![Признак обязательности ЭЦП])",
          "OnExitEmMacro" : "",
          "ControlTipText" : "",
          "TabIndex" : 2,
          "TabStop" : "true",
          "StatusBarText" : "Признак обязательности ЭП после утверждения",
          "ShortcutMenuBar" : "",
          "HelpContextId" : 0,
          "Tag" : "",
          "ColumnWidth" : -1,
          "ColumnOrder" : 0,
          "ColumnHidden" : "false",
          "Section" : 0,
          "InSelection" : "false",
          "AggregateType" : -1,
          "Layout" : 0,
          "LayoutID" : 0
        }
      },
      "Рамка Признак проверки ЭЦП" : {
        "Properties" : {
          "EventProcPrefix" : "Рамка_Признак_проверки_ЭЦП",
          "Name" : "Рамка Признак проверки ЭЦП",
          "ControlType" : 101,
          "Visible" : "true",
          "Width" : 512,
          "Height" : 240,
          "Top" : 0,
          "Left" : 5850,
          "BackStyle" : 0,
          "BackColor" : 16777215,
          "BorderStyle" : 1,
          "OldBorderStyle" : 1,
          "BorderLineStyle" : 0,
          "BorderWidth" : 0,
          "BorderColor" : -2147483609,
          "SpecialEffect" : 0,
          "GridlineStyleTop" : 0,
          "GridlineStyleBottom" : 0,
          "GridlineStyleLeft" : 0,
          "GridlineStyleRight" : 0,
          "GridlineColor" : 0,
          "GridlineWidthTop" : 1,
          "GridlineWidthBottom" : 1,
          "GridlineWidthLeft" : 1,
          "GridlineWidthRight" : 1,
          "TopPadding" : 30,
          "BottomPadding" : 30,
          "LeftPadding" : 30,
          "RightPadding" : 30,
          "HorizontalAnchor" : 1,
          "VerticalAnchor" : 0,
          "DisplayWhen" : 0,
          "OnClick" : "",
          "OnClickEmMacro" : "",
          "OnDblClick" : "",
          "OnDblClickEmMacro" : "",
          "OnMouseDown" : "",
          "OnMouseDownEmMacro" : "",
          "OnMouseUp" : "",
          "OnMouseUpEmMacro" : "",
          "OnMouseMove" : "",
          "OnMouseMoveEmMacro" : "",
          "Tag" : "",
          "Section" : 0,
          "InSelection" : "false",
          "Layout" : 0,
          "LayoutID" : 0
        }
      },
      "Признак проверки ЭЦП" : {
        "Properties" : {
          "EventProcPrefix" : "Признак_проверки_ЭЦП",
          "Name" : "Признак проверки ЭЦП",
          "ControlType" : 106,
          "ControlSource" : "Признак проверки ЭЦП",
          "Visible" : "true",
          "TripleState" : "false",
          "Width" : 170,
          "Height" : 180,
          "Top" : 45,
          "Left" : 6028,
          "BorderStyle" : 1,
          "OldBorderStyle" : 1,
          "BorderLineStyle" : 0,
          "BorderWidth" : 0,
          "BorderColor" : 0,
          "SpecialEffect" : 5,
          "GridlineStyleTop" : 0,
          "GridlineStyleBottom" : 0,
          "GridlineStyleLeft" : 0,
          "GridlineStyleRight" : 0,
          "GridlineColor" : 0,
          "GridlineWidthTop" : 1,
          "GridlineWidthBottom" : 1,
          "GridlineWidthLeft" : 1,
          "GridlineWidthRight" : 1,
          "TopPadding" : 30,
          "BottomPadding" : 30,
          "LeftPadding" : 30,
          "RightPadding" : 30,
          "HorizontalAnchor" : 1,
          "VerticalAnchor" : 0,
          "DisplayWhen" : 0,
          "ReadingOrder" : 0,
          "DefaultValue" : "",
          "ValidationRule" : "",
          "ValidationText" : "",
          "Enabled" : "false",
          "Locked" : "false",
          "OnClick" : "",
          "OnClickEmMacro" : "",
          "BeforeUpdate" : "",
          "BeforeUpdateEmMacro" : "",
          "AfterUpdate" : "=Inputs_OnControlAfterUpdate([Form]![Признак проверки ЭЦП])",
          "AfterUpdateEmMacro" : "",
          "OnGotFocus" : "",
          "OnGotFocusEmMacro" : "",
          "OnLostFocus" : "",
          "OnLostFocusEmMacro" : "",
          "OnDblClick" : "=Inputs_OnControlDblClick([Form]![Признак проверки ЭЦП])",
          "OnDblClickEmMacro" : "",
          "OnMouseDown" : "",
          "OnMouseDownEmMacro" : "",
          "OnMouseUp" : "",
          "OnMouseUpEmMacro" : "",
          "OnMouseMove" : "",
          "OnMouseMoveEmMacro" : "",
          "OnKeyDown" : "",
          "OnKeyDownEmMacro" : "",
          "OnKeyUp" : "",
          "OnKeyUpEmMacro" : "",
          "OnKeyPress" : "",
          "OnKeyPressEmMacro" : "",
          "OnEnter" : "=Inputs_OnControlEnter([Form]![Признак проверки ЭЦП])",
          "OnEnterEmMacro" : "",
          "OnExit" : "=Inputs_OnControlExit([Form]![Признак проверки ЭЦП])",
          "OnExitEmMacro" : "",
          "ControlTipText" : "",
          "TabIndex" : 10,
          "TabStop" : "true",
          "StatusBarText" : "Признак проверки ЭП",
          "ShortcutMenuBar" : "",
          "HelpContextId" : 0,
          "Tag" : "",
          "ColumnWidth" : -1,
          "ColumnOrder" : 0,
          "ColumnHidden" : "false",
          "Section" : 0,
          "InSelection" : "false",
          "AggregateType" : -1,
          "Layout" : 0,
          "LayoutID" : 0
        }
      },
      "Всего записей" : {
        "Properties" : {
          "EventProcPrefix" : "Всего_записей",
          "Name" : "Всего записей",
          "ControlType" : 109,
          "ControlSource" : "=Count(*)",
          "Format" : "",
          "DecimalPlaces" : 255,
          "Visible" : "true",
          "TextFormat" : 0,
          "DatasheetCaption" : "",
          "ShowDatePicker" : 1,
          "Width" : 1047,
          "Height" : 240,
          "Top" : 0,
          "Left" : 1335,
          "BackStyle" : 0,
          "BackColor" : -2147483643,
          "BorderStyle" : 0,
          "OldBorderStyle" : 0,
          "BorderLineStyle" : 0,
          "BorderWidth" : 0,
          "BorderColor" : -2147483609,
          "SpecialEffect" : 0,
          "ScrollBars" : 0,
          "TextFontCharSet" : 204,
          "FontName" : "MS Sans Serif",
          "FontSize" : 8,
          "TextAlign" : 1,
          "FontWeight" : 400,
          "FontUnderline" : "false",
          "FontItalic" : "false",
          "FontBold" : 0,
          "ForeColor" : 0,
          "LineSpacing" : 0,
          "IsHyperlink" : "false",
          "DisplayAsHyperlink" : 0,
          "GridlineStyleTop" : 0,
          "GridlineStyleBottom" : 0,
          "GridlineStyleLeft" : 0,
          "GridlineStyleRight" : 0,
          "GridlineColor" : 0,
          "GridlineWidthTop" : 1,
          "GridlineWidthBottom" : 1,
          "GridlineWidthLeft" : 1,
          "GridlineWidthRight" : 1,
          "TopMargin" : 0,
          "BottomMargin" : 0,
          "LeftMargin" : 0,
          "RightMargin" : 0,
          "TopPadding" : 30,
          "BottomPadding" : 30,
          "LeftPadding" : 30,
          "RightPadding" : 30,
          "HorizontalAnchor" : 0,
          "VerticalAnchor" : 0,
          "CanGrow" : "false",
          "CanShrink" : "false",
          "DisplayWhen" : 0,
          "ReadingOrder" : 0,
          "ScrollBarAlign" : 0,
          "NumeralShapes" : 0,
          "KeyboardLanguage" : 0,
          "InputMask" : "",
          "DefaultValue" : "",
          "ValidationRule" : "",
          "ValidationText" : "",
          "FilterLookup" : 1,
          "Enabled" : "false",
          "Locked" : "true",
          "OnClick" : "",
          "OnClickEmMacro" : "",
          "BeforeUpdate" : "",
          "BeforeUpdateEmMacro" : "",
          "AfterUpdate" : "",
          "AfterUpdateEmMacro" : "",
          "OnDirty" : "",
          "OnDirtyEmMacro" : "",
          "OnChange" : "",
          "OnChangeEmMacro" : "",
          "OnGotFocus" : "",
          "OnGotFocusEmMacro" : "",
          "OnLostFocus" : "",
          "OnLostFocusEmMacro" : "",
          "OnDblClick" : "",
          "OnDblClickEmMacro" : "",
          "OnMouseDown" : "",
          "OnMouseDownEmMacro" : "",
          "OnMouseUp" : "",
          "OnMouseUpEmMacro" : "",
          "OnMouseMove" : "",
          "OnMouseMoveEmMacro" : "",
          "OnKeyDown" : "",
          "OnKeyDownEmMacro" : "",
          "OnKeyUp" : "",
          "OnKeyUpEmMacro" : "",
          "OnKeyPress" : "",
          "OnKeyPressEmMacro" : "",
          "OnEnter" : "",
          "OnEnterEmMacro" : "",
          "OnExit" : "",
          "OnExitEmMacro" : "",
          "OnUndo" : "",
          "OnUndoEmMacro" : "",
          "EnterKeyBehavior" : "false",
          "ControlTipText" : "",
          "TabIndex" : 0,
          "TabStop" : "false",
          "StatusBarText" : "",
          "ShortcutMenuBar" : "",
          "HelpContextId" : 0,
          "AutoTab" : "false",
          "Vertical" : "false",
          "AllowAutoCorrect" : "true",
          "IMEHold" : "false",
          "IMEMode" : 0,
          "IMESentenceMode" : 0,
          "SmartTags" : "",
          "Tag" : "",
          "ConditionalFormat" : "Null",
          "FuriganaControl" : "",
          "ColumnWidth" : -1,
          "ColumnOrder" : 0,
          "ColumnHidden" : "false",
          "Section" : 2,
          "Text" : "Null",
          "SelText" : "Null",
          "SelStart" : "Null",
          "SelLength" : "Null",
          "InSelection" : "false",
          "AggregateType" : -1,
          "Layout" : 0,
          "LayoutID" : 0
        }
      },
      "Надпись Всего записей" : {
        "Properties" : {
          "EventProcPrefix" : "Надпись_Всего_записей",
          "Name" : "Надпись Всего записей",
          "ControlType" : 100,
          "Caption" : "Всего полей:",
          "Visible" : "true",
          "Width" : 1350,
          "Height" : 240,
          "Top" : 0,
          "Left" : -15,
          "BackStyle" : 0,
          "BackColor" : -2147483633,
          "BorderStyle" : 0,
          "OldBorderStyle" : 0,
          "BorderLineStyle" : 0,
          "BorderWidth" : 0,
          "BorderColor" : -2147483609,
          "SpecialEffect" : 0,
          "TextFontCharSet" : 204,
          "FontName" : "MS Sans Serif",
          "FontSize" : 8,
          "TextAlign" : 3,
          "FontWeight" : 400,
          "FontUnderline" : "false",
          "FontItalic" : "false",
          "FontBold" : 0,
          "ForeColor" : 0,
          "LineSpacing" : 0,
          "HyperlinkAddress" : "",
          "HyperlinkSubAddress" : "",
          "GridlineStyleTop" : 0,
          "GridlineStyleBottom" : 0,
          "GridlineStyleLeft" : 0,
          "GridlineStyleRight" : 0,
          "GridlineColor" : 0,
          "GridlineWidthTop" : 1,
          "GridlineWidthBottom" : 1,
          "GridlineWidthLeft" : 1,
          "GridlineWidthRight" : 1,
          "TopMargin" : 0,
          "BottomMargin" : 0,
          "LeftMargin" : 0,
          "RightMargin" : 0,
          "TopPadding" : 30,
          "BottomPadding" : 30,
          "LeftPadding" : 30,
          "RightPadding" : 30,
          "HorizontalAnchor" : 0,
          "VerticalAnchor" : 0,
          "DisplayWhen" : 0,
          "ReadingOrder" : 0,
          "NumeralShapes" : 0,
          "OnClick" : "",
          "OnClickEmMacro" : "",
          "OnDblClick" : "",
          "OnDblClickEmMacro" : "",
          "OnMouseDown" : "",
          "OnMouseDownEmMacro" : "",
          "OnMouseUp" : "",
          "OnMouseUpEmMacro" : "",
          "OnMouseMove" : "",
          "OnMouseMoveEmMacro" : "",
          "ControlTipText" : "",
          "ShortcutMenuBar" : "",
          "HelpContextId" : 0,
          "Vertical" : "false",
          "SmartTags" : "",
          "Tag" : "",
          "Section" : 2,
          "InSelection" : "false",
          "Layout" : 0,
          "LayoutID" : 0
        }
      }
    }
  },
  "Menu_number" : [ ]
}